Workbook
Name 时点法: 【2026年】前向收入合同审签表!#REF!
Name 时段法: 【2026年】前向收入合同审签表!#REF!

Sheet 【2026年】前向收入合同审签表
A1: 前向收入合同审签表（2026）
A2: 收入确认计划 | B2: 必填 | C2: 选择填列 | D2: 必选 | E2: 自动带出 可修改 | F2: 自动带出 | G2: 选择填列 | H2: 自动带出 | I2: 选择填列 | J2: 自动带出 | K2: 必填 | L2: 选择填列 | M2: 自动带出 | N2: 自动带出 | O2: 自动带出 可修改 | P2: 收入确认计划 | Q2: 必填 | R2: 必填 | S2: 必选 | T2: 自动带出 可修改 | U2: 自动带出 | V2: 选择填列 | W2: 自动带出 | X2: 选择填列 | Y2: 自动带出 | Z2: 必填 | AA2: 必填 | AB2: 必填 | AC2: 公式自动算出 | AD2: 自动带出 | AE2: 自动带出 | AF2: 自动带出 可修改
A3: 非周期性 序号 | B3: 业务模式与列收方式 | C3: 预计确认日期 YYYY-MM-DD | D3: 集团产品名称 | E3: 集团产品收入项 | F3: 速率/带宽 填写提示 （在G列）→ | G3: 速率/带宽 收入项为电路及专线必填 | H3: 折扣率 填写提示 （在I列）→ | I3: 折扣率 物联网卡必填 | J3: 税率 | K3: 计划确认总金额 (含税) | L3: 填列跨省省份名称 按分摊金额分开填列 跨省电路业务必填 | M3: 业务收入对象分类 标品不触发应收任务单 | N3: 是否 网元开通 | O3: 是否CRM 确认收入 | P3: 周期性 序号 | Q3: 业务模式与列收方式 | R3: 起始日期 YYYY-MM-DD | S3: 集团产品名称 | T3: 集团产品收入项 | U3: 速率/带宽 填写提示 (在T列）→ | V3: 速率/带宽 收入项为电路及专线必填 | W3: 折扣率 填写提示 (在V列）→ | X3: 折扣率 物联网卡必填 | Y3: 税率 | Z3: 收入确认 总时长 （月） | AA3: 每月单价 | AB3: 产品数量 | AC3: 确认总金额 (含税) | AD3: 业务收入对象分类 标品不触发应收任务单 | AE3: 是否 网元开通 | AF3: 是否CRM 确认收入
A4: 1 | B4: 服务整合、总额法、时点法 | D4: MSTP-本地电路 | E4: =IFERROR(VLOOKUP(D4,【2026年】集团产品与集团产品收入项配置表!D:M,10,FALSE),"选择集团产品名称后自动带出") -> 3059(标）、3092(项) | F4: =IFERROR(VLOOKUP(D4,【2026年】集团产品与集团产品收入项配置表!D:T,17,FALSE),"选择集团产品名称后自动带出") -> 需填写速率/带宽 | H4: =IFERROR(VLOOKUP(D4,【2026年】集团产品与集团产品收入项配置表!D:U,18,FALSE),"选择集团产品名称后自动带出") -> 无需填写折扣率 | J4: =IFERROR(VLOOKUP(D4,【2026年】集团产品与集团产品收入项配置表!D:N,11,FALSE),"选择集团产品名称后自动带出") -> 0.09 | M4: =IFERROR(VLOOKUP(D4,【2026年】集团产品与集团产品收入项配置表!D:F,3,FALSE),"选择集团产品名称后自动带出") -> 标品 | N4: =IFERROR(VLOOKUP(D4,【2026年】集团产品与集团产品收入项配置表!D:R,15,FALSE),"选择集团产品名称后自动带出") -> 是 | O4: =IFERROR(VLOOKUP(D4,【2026年】集团产品与集团产品收入项配置表!D:S,16,FALSE),"选择集团产品名称后自动带出") -> 是 | P4: 1 | Q4: 服务整合、总额法、时段法 | S4: MSTP-本地电路 | T4: =IFERROR(VLOOKUP(S4,【2026年】集团产品与集团产品收入项配置表!D:M,10,FALSE),"选择集团产品名称后自动带出") -> 3059(标）、3092(项) | U4: =IFERROR(VLOOKUP(S4,【2026年】集团产品与集团产品收入项配置表!D:T,17,FALSE),"选择集团产品名称后自动带出") -> 需填写速率/带宽 | W4: =IFERROR(VLOOKUP(S4,【2026年】集团产品与集团产品收入项配置表!D:U,18,FALSE),"选择集团产品名称后自动带出") -> 无需填写折扣率 | Y4: =IFERROR(VLOOKUP(S4,【2026年】集团产品与集团产品收入项配置表!D:N,11,FALSE),"选择集团产品名称后自动带出") -> 0.09 | AC4: =AA4*AB4*Z4 -> 0 | AD4: =IFERROR(VLOOKUP(S4,【2026年】集团产品与集团产品收入项配置表!D:F,3,FALSE),"选择集团产品名称后自动带出") -> 标品 | AE4: =IFERROR(VLOOKUP(S4,【2026年】集团产品与集团产品收入项配置表!D:R,15,FALSE),"选择集团产品名称后自动带出") -> 是 | AF4: =IFERROR(VLOOKUP(S4,【2026年】集团产品与集团产品收入项配置表!D:S,16,FALSE),"选择集团产品名称后自动带出") -> 是
A5: 2 | E5: =IFERROR(VLOOKUP(D5,【2026年】集团产品与集团产品收入项配置表!D:M,10,FALSE),"选择集团产品名称后自动带出") -> 选择集团产品名称后自动带出 | F5: =IFERROR(VLOOKUP(D5,【2026年】集团产品与集团产品收入项配置表!D:T,17,FALSE),"选择集团产品名称后自动带出") -> 选择集团产品名称后自动带出 | H5: =IFERROR(VLOOKUP(D5,【2026年】集团产品与集团产品收入项配置表!D:U,18,FALSE),"选择集团产品名称后自动带出") -> 选择集团产品名称后自动带出 | J5: =IFERROR(VLOOKUP(D5,【2026年】集团产品与集团产品收入项配置表!D:N,11,FALSE),"选择集团产品名称后自动带出") -> 选择集团产品名称后自动带出 | M5: =IFERROR(VLOOKUP(D5,【2026年】集团产品与集团产品收入项配置表!D:F,3,FALSE),"选择集团产品名称后自动带出") -> 选择集团产品名称后自动带出 | N5: =IFERROR(VLOOKUP(D5,【2026年】集团产品与集团产品收入项配置表!D:R,15,FALSE),"选择集团产品名称后自动带出") -> 选择集团产品名称后自动带出 | O5: =IFERROR(VLOOKUP(D5,【2026年】集团产品与集团产品收入项配置表!D:S,16,FALSE),"选择集团产品名称后自动带出") -> 选择集团产品名称后自动带出 | P5: 2 | T5: =IFERROR(VLOOKUP(S5,【2026年】集团产品与集团产品收入项配置表!D:M,10,FALSE),"选择集团产品名称后自动带出") -> 选择集团产品名称后自动带出 | U5: =IFERROR(VLOOKUP(S5,【2026年】集团产品与集团产品收入项配置表!D:T,17,FALSE),"选择集团产品名称后自动带出") -> 选择集团产品名称后自动带出 | W5: =IFERROR(VLOOKUP(S5,【2026年】集团产品与集团产品收入项配置表!D:U,18,FALSE),"选择集团产品名称后自动带出") -> 选择集团产品名称后自动带出 | Y5: =IFERROR(VLOOKUP(S5,【2026年】集团产品与集团产品收入项配置表!D:N,11,FALSE),"选择集团产品名称后自动带出") -> 选择集团产品名称后自动带出 | AC5: =AA5*AB5*Z5 -> 0 | AD5: =IFERROR(VLOOKUP(S5,【2026年】集团产品与集团产品收入项配置表!D:F,3,FALSE),"选择集团产品名称后自动带出") -> 选择集团产品名称后自动带出 | AE5: =IFERROR(VLOOKUP(S5,【2026年】集团产品与集团产品收入项配置表!D:R,15,FALSE),"选择集团产品名称后自动带出") -> 选择集团产品名称后自动带出 | AF5: =IFERROR(VLOOKUP(S5,【2026年】集团产品与集团产品收入项配置表!D:S,16,FALSE),"选择集团产品名称后自动带出") -> 选择集团产品名称后自动带出
A6: 3 | E6: =IFERROR(VLOOKUP(D6,【2026年】集团产品与集团产品收入项配置表!D:M,10,FALSE),"选择集团产品名称后自动带出") -> 选择集团产品名称后自动带出 | F6: =IFERROR(VLOOKUP(D6,【2026年】集团产品与集团产品收入项配置表!D:T,17,FALSE),"选择集团产品名称后自动带出") -> 选择集团产品名称后自动带出 | H6: =IFERROR(VLOOKUP(D6,【2026年】集团产品与集团产品收入项配置表!D:U,18,FALSE),"选择集团产品名称后自动带出") -> 选择集团产品名称后自动带出 | J6: =IFERROR(VLOOKUP(D6,【2026年】集团产品与集团产品收入项配置表!D:N,11,FALSE),"选择集团产品名称后自动带出") -> 选择集团产品名称后自动带出 | M6: =IFERROR(VLOOKUP(D6,【2026年】集团产品与集团产品收入项配置表!D:F,3,FALSE),"选择集团产品名称后自动带出") -> 选择集团产品名称后自动带出 | N6: =IFERROR(VLOOKUP(D6,【2026年】集团产品与集团产品收入项配置表!D:R,15,FALSE),"选择集团产品名称后自动带出") -> 选择集团产品名称后自动带出 | O6: =IFERROR(VLOOKUP(D6,【2026年】集团产品与集团产品收入项配置表!D:S,16,FALSE),"选择集团产品名称后自动带出") -> 选择集团产品名称后自动带出 | P6: 3 | T6: =IFERROR(VLOOKUP(S6,【2026年】集团产品与集团产品收入项配置表!D:M,10,FALSE),"选择集团产品名称后自动带出") -> 选择集团产品名称后自动带出 | U6: =IFERROR(VLOOKUP(S6,【2026年】集团产品与集团产品收入项配置表!D:T,17,FALSE),"选择集团产品名称后自动带出") -> 选择集团产品名称后自动带出 | W6: =IFERROR(VLOOKUP(S6,【2026年】集团产品与集团产品收入项配置表!D:U,18,FALSE),"选择集团产品名称后自动带出") -> 选择集团产品名称后自动带出 | Y6: =IFERROR(VLOOKUP(S6,【2026年】集团产品与集团产品收入项配置表!D:N,11,FALSE),"选择集团产品名称后自动带出") -> 选择集团产品名称后自动带出 | AC6: =AA6*AB6*Z6 -> 0 | AD6: =IFERROR(VLOOKUP(S6,【2026年】集团产品与集团产品收入项配置表!D:F,3,FALSE),"选择集团产品名称后自动带出") -> 选择集团产品名称后自动带出 | AE6: =IFERROR(VLOOKUP(S6,【2026年】集团产品与集团产品收入项配置表!D:R,15,FALSE),"选择集团产品名称后自动带出") -> 选择集团产品名称后自动带出 | AF6: =IFERROR(VLOOKUP(S6,【2026年】集团产品与集团产品收入项配置表!D:S,16,FALSE),"选择集团产品名称后自动带出") -> 选择集团产品名称后自动带出
A7: 4 | E7: =IFERROR(VLOOKUP(D7,【2026年】集团产品与集团产品收入项配置表!D:M,10,FALSE),"选择集团产品名称后自动带出") -> 选择集团产品名称后自动带出 | F7: =IFERROR(VLOOKUP(D7,【2026年】集团产品与集团产品收入项配置表!D:T,17,FALSE),"选择集团产品名称后自动带出") -> 选择集团产品名称后自动带出 | H7: =IFERROR(VLOOKUP(D7,【2026年】集团产品与集团产品收入项配置表!D:U,18,FALSE),"选择集团产品名称后自动带出") -> 选择集团产品名称后自动带出 | J7: =IFERROR(VLOOKUP(D7,【2026年】集团产品与集团产品收入项配置表!D:N,11,FALSE),"选择集团产品名称后自动带出") -> 选择集团产品名称后自动带出 | M7: =IFERROR(VLOOKUP(D7,【2026年】集团产品与集团产品收入项配置表!D:F,3,FALSE),"选择集团产品名称后自动带出") -> 选择集团产品名称后自动带出 | N7: =IFERROR(VLOOKUP(D7,【2026年】集团产品与集团产品收入项配置表!D:R,15,FALSE),"选择集团产品名称后自动带出") -> 选择集团产品名称后自动带出 | O7: =IFERROR(VLOOKUP(D7,【2026年】集团产品与集团产品收入项配置表!D:S,16,FALSE),"选择集团产品名称后自动带出") -> 选择集团产品名称后自动带出 | P7: 4 | T7: =IFERROR(VLOOKUP(S7,【2026年】集团产品与集团产品收入项配置表!D:M,10,FALSE),"选择集团产品名称后自动带出") -> 选择集团产品名称后自动带出 | U7: =IFERROR(VLOOKUP(S7,【2026年】集团产品与集团产品收入项配置表!D:T,17,FALSE),"选择集团产品名称后自动带出") -> 选择集团产品名称后自动带出 | W7: =IFERROR(VLOOKUP(S7,【2026年】集团产品与集团产品收入项配置表!D:U,18,FALSE),"选择集团产品名称后自动带出") -> 选择集团产品名称后自动带出 | Y7: =IFERROR(VLOOKUP(S7,【2026年】集团产品与集团产品收入项配置表!D:N,11,FALSE),"选择集团产品名称后自动带出") -> 选择集团产品名称后自动带出 | AC7: =AA7*AB7*Z7 -> 0 | AD7: =IFERROR(VLOOKUP(S7,【2026年】集团产品与集团产品收入项配置表!D:F,3,FALSE),"选择集团产品名称后自动带出") -> 选择集团产品名称后自动带出 | AE7: =IFERROR(VLOOKUP(S7,【2026年】集团产品与集团产品收入项配置表!D:R,15,FALSE),"选择集团产品名称后自动带出") -> 选择集团产品名称后自动带出 | AF7: =IFERROR(VLOOKUP(S7,【2026年】集团产品与集团产品收入项配置表!D:S,16,FALSE),"选择集团产品名称后自动带出") -> 选择集团产品名称后自动带出
A8: 5 | E8: =IFERROR(VLOOKUP(D8,【2026年】集团产品与集团产品收入项配置表!D:M,10,FALSE),"选择集团产品名称后自动带出") -> 选择集团产品名称后自动带出 | F8: =IFERROR(VLOOKUP(D8,【2026年】集团产品与集团产品收入项配置表!D:T,17,FALSE),"选择集团产品名称后自动带出") -> 选择集团产品名称后自动带出 | H8: =IFERROR(VLOOKUP(D8,【2026年】集团产品与集团产品收入项配置表!D:U,18,FALSE),"选择集团产品名称后自动带出") -> 选择集团产品名称后自动带出 | J8: =IFERROR(VLOOKUP(D8,【2026年】集团产品与集团产品收入项配置表!D:N,11,FALSE),"选择集团产品名称后自动带出") -> 选择集团产品名称后自动带出 | M8: =IFERROR(VLOOKUP(D8,【2026年】集团产品与集团产品收入项配置表!D:F,3,FALSE),"选择集团产品名称后自动带出") -> 选择集团产品名称后自动带出 | N8: =IFERROR(VLOOKUP(D8,【2026年】集团产品与集团产品收入项配置表!D:R,15,FALSE),"选择集团产品名称后自动带出") -> 选择集团产品名称后自动带出 | O8: =IFERROR(VLOOKUP(D8,【2026年】集团产品与集团产品收入项配置表!D:S,16,FALSE),"选择集团产品名称后自动带出") -> 选择集团产品名称后自动带出 | P8: 5 | T8: =IFERROR(VLOOKUP(S8,【2026年】集团产品与集团产品收入项配置表!D:M,10,FALSE),"选择集团产品名称后自动带出") -> 选择集团产品名称后自动带出 | U8: =IFERROR(VLOOKUP(S8,【2026年】集团产品与集团产品收入项配置表!D:T,17,FALSE),"选择集团产品名称后自动带出") -> 选择集团产品名称后自动带出 | W8: =IFERROR(VLOOKUP(S8,【2026年】集团产品与集团产品收入项配置表!D:U,18,FALSE),"选择集团产品名称后自动带出") -> 选择集团产品名称后自动带出 | Y8: =IFERROR(VLOOKUP(S8,【2026年】集团产品与集团产品收入项配置表!D:N,11,FALSE),"选择集团产品名称后自动带出") -> 选择集团产品名称后自动带出 | AC8: =AA8*AB8*Z8 -> 0 | AD8: =IFERROR(VLOOKUP(S8,【2026年】集团产品与集团产品收入项配置表!D:F,3,FALSE),"选择集团产品名称后自动带出") -> 选择集团产品名称后自动带出 | AE8: =IFERROR(VLOOKUP(S8,【2026年】集团产品与集团产品收入项配置表!D:R,15,FALSE),"选择集团产品名称后自动带出") -> 选择集团产品名称后自动带出 | AF8: =IFERROR(VLOOKUP(S8,【2026年】集团产品与集团产品收入项配置表!D:S,16,FALSE),"选择集团产品名称后自动带出") -> 选择集团产品名称后自动带出
A9: 合 计 | K9: =SUM(K4:K8) -> 0 | P9: 合 计 | AC9: =SUM(AC4:AC8) -> 0
A11: 是否有 履约保证金 | C11: 是否有 维保要求 | E11: 是否有 审计条款 | G11: 发票种类 （必选） | H11: 增值税专用发票 | I11: 该合同实际 利润归属单位 （必选） | J11: 智慧商务部/号百公司
A13: 收款计划 | B13: 必填 | C13: 必选 | D13: 必填 | E13: 必选 | F13: 按比例收款 时必填 | G13: 必填 | H13: 必选 | I13: 收款计划 | J13: 必填 | K13: 必选 | L13: 必填 | M13: 必填 | N13: 公式自动算出 | O13: 必选
A14: 非周期性 序号 | B14: 预计收款日期 YYYY-MM-DD | C14: 非周期 收款方式 | D14: 第N次 | E14: 履行要求 | F14: 约定收款 比例 | G14: 约定收款 金额 | H14: 收款 触发系统 | I14: 周期性 序号 | J14: 预计收款 起始日期 YYYY-MM-DD | K14: 收款频率 （周期方式） | L14: 期数 | M14: 每期金额 | N14: 金额合计 | O14: 收款 触发系统
A15: 1 | I15: 1 | N15: =L15*M15 -> 0
A16: 2 | I16: 2 | N16: =L16*M16 -> 0
A17: 3 | I17: 3 | N17: =L17*M17 -> 0
A18: 4 | I18: 4 | N18: =L18*M18 -> 0
A19: 5 | I19: 5 | N19: =L19*M19 -> 0
A20: 合 计 | F20: =SUM(F15:F19) -> 0 | G20: =SUM(G15:G19) -> 0 | I20: 合 计 | N20: =SUM(N15:N19) -> 0
A22: 填表人： （必填） | B22: 王照龙 | C22: 联系方式： （必填） | D22: 02152927531 | E22: 项目立项人: （必填） | F22: 王照龙 | G22: 联系方式： （必填） | H22: 02152927531
A25: 填表说明：
A26: 1、若涉及多项产品收入项的请分行填列，小计金额需与合同金额一致。
A27: 2、若合同履约信息即有非周期性也有周期性，则在相应表格中填列。
A28: 3、若该合同有跨利润中心的情况，请填列“该合同实际利润归属单位”信息，不然合同解析利润中心默认为合同发起单位。
A29: 4、若非周期收款方式为按金额收款的，表格中约定收款比例可不填列。
A30: 5、“是否有履约保证金”、“是否有维保要求”及“是否有审计条款”默认为“否”，若该合同涉及此3项有实际发生的请改为“是”并附相应情况说明。
A31: 6、由于目前部分产品较个性化，不具备标准化资费的条件，无法走CRM系统开账，而通过聚焦系统开账会虚增应收账款，因此选“非CRM确认收入”的合同，其实际履约信息若为周期性的，一律解析为非周期性。
A32: 7、集团要求按月确认收入的为收入周期性，除此之外均为非周期性收入；而收款方式的频率若为按月、按季、按半年、按年则均为周期性收款。
A33: 8、集团要求涉及电路及专线类收入项的话，速率及带宽为必填，涉及物联网收入项的话，折扣率为必填。
A34: 9、跨省电路业务新增“跨省省份”列，请按分摊金额分开填列。

Sheet 【2026年】集团产品与集团产品收入项配置表
A1: 产品大类编码（修订） | B1: 产品大类（修订） | C1: 产品编码 | D1: 产品名称 | E1: 是否ICT产品 | F1: 是否标品 | G1: 单位 | H1: 注释 | I1: 产品类型 | J1: 产品类别 | K1: 平台类型编码 | L1: 平台类型 名称 | M1: 默认带出的产品收入项2026 | N1: 税率 | O1: 默认带出的产品收入项名称2026 （ICT合同中含IDC、组网专线、物联网、5G定制网内容需调整为“项目型”） | P1: 可选产品收入项范围编码2026 | Q1: 可选产品收入项范围2026 | R1: 是否网元 | S1: 是否触发CRM | T1: 速率/带宽 填写提示 | U1: 折扣率 填写提示
A2: JTSJCPDL201915 | B2: 云网融合业务 | C2: JTSJCP02222 | D2: 教育专网（统筹省级） | E2: 是 | F2: 标品 | I2: 云业务 | J2: ICT | L2: 专线接入成本 | M2: 3077(标）、3110(项) | N2: 0.09 | O2: 产业数字化-资源型服务-组网专线-标品型-普通组网专线-普通组网专线-其他 | P2: 3077 | Q2: 产业数字化-资源型服务-组网专线-标品型-普通组网专线-其他 | R2: 是 | S2: 是 | T2: 需填写速率/带宽 | U2: 无需填写折扣率
A3: JTSJCPDL201915 | B3: 云网融合业务 | C3: JTSJCP02223 | D3: FIRST金融专网 | E3: 是 | F3: 标品 | I3: 云业务 | J3: ICT | L3: 专线接入成本 | M3: 3077(标）、3110(项) | N3: 0.09 | O3: 产业数字化-资源型服务-组网专线-标品型-普通组网专线-普通组网专线-其他 | P3: 3077 | Q3: 产业数字化-资源型服务-组网专线-标品型-普通组网专线-其他 | R3: 是 | S3: 是 | T3: 需填写速率/带宽 | U3: 无需填写折扣率
A4: JTSJCPDL201915 | B4: 云网融合业务 | C4: JTSJCP02225 | D4: 视频专网（统筹省级） | E4: 是 | F4: 标品 | I4: 云业务 | J4: ICT | L4: 专线接入成本 | M4: 3077(标）、3110(项) | N4: 0.09 | O4: 产业数字化-资源型服务-组网专线-标品型-普通组网专线-普通组网专线-其他 | P4: 3077 | Q4: 产业数字化-资源型服务-组网专线-标品型-普通组网专线-其他 | R4: 是 | S4: 是 | T4: 需填写速率/带宽 | U4: 无需填写折扣率
A5: JTSJCPDL201915 | B5: 云网融合业务 | C5: JTSJCP02227 | D5: 云专网 | E5: 是 | F5: 标品 | I5: 云业务 | J5: ICT | L5: 专线接入成本 | M5: 3077(标）、3110(项) | N5: 0.09 | O5: 产业数字化-资源型服务-组网专线-标品型-普通组网专线-普通组网专线-其他 | P5: 3077 | Q5: 产业数字化-资源型服务-组网专线-标品型-普通组网专线-其他 | R5: 是 | S5: 是 | T5: 需填写速率/带宽 | U5: 无需填写折扣率
A6: JTSJCPDL201915 | B6: 云网融合业务 | C6: JTSJCP02226 | D6: 物联专网（统筹省级） | E6: 是 | F6: 标品 | I6: 云业务 | J6: ICT | L6: 专线接入成本 | M6: 2891 | N6: 0.06 | O6: 产业数字化-资源型服务-物联网-项目型物联网-其他 | P6: 2891 | Q6: 产业数字化-资源型服务-物联网-项目型物联网-其他 | R6: 是 | S6: 是 | T6: 需填写速率/带宽 | U6: 无需填写折扣率
A7: JTSJCPDL201915 | B7: 云网融合业务 | C7: JTSJCP02228 | D7: 智能专线 | E7: 是 | F7: 标品 | I7: 云业务 | J7: ICT | L7: 专线接入成本 | M7: 2967 | N7: 0.06 | O7: 产业数字化-ICT业务-行业云产品-项目中公有云产品-IaaS-云网服务-其他-自研 | P7: 2967 | Q7: 产业数字化-ICT业务-行业云产品-项目中公有云产品-IaaS-云网服务-其他-自研 | R7: 是 | S7: 是 | T7: 需填写速率/带宽 | U7: 无需填写折扣率
A8: JTSJCPDL201914 | B8: 其它业务 | C8: JTSJCP03007 | D8: 房地产出租 | E8: 否 | F8: 其他 | G8: - | H8: - | I8: 房屋租赁 | M8: 1763 | N8: 9%、5% | O8: 其他-固网其他-出租房产场地收入 | P8: 1763 | R8: 否 | S8: 否 | T8: 无需填写速率/带宽 | U8: 无需填写折扣率
A9: JTSJCPDL201913 | B9: 其他固网业务 | C9: JTSJCP02078 | D9: 设备出售 | E9: 否 | F9: 设备 | G9: - | H9: - | I9: 外延业务 | M9: 3212 | N9: 0.13 | O9: 其他-固网其他-实物商品销售-系统集成-其他 | P9: 3212 | Q9: 其他-固网其他-实物商品销售-系统集成-其他 | R9: 否 | S9: 否 | T9: 无需填写速率/带宽 | U9: 无需填写折扣率
A10: JTSJCPDL201913 | B10: 其他固网业务 | C10: JTSJCP02043 | D10: 普通电话 | E10: 否 | F10: 标品 | G10: 部 | H10: 电话数 | I10: 外延业务 | M10: 1221 | N10: 0.06 | O10: 固网及智慧家庭服务-固定电话-固网语音 | P10: 1221 | Q10: 固网及智慧家庭服务-固定电话-固网语音 | R10: 是 | S10: 是 | T10: 无需填写速率/带宽 | U10: 无需填写折扣率
A11: JTSJCPDL201913 | B11: 其他固网业务 | C11: JTSJCP02044 | D11: 语音中继线 | E11: 否 | F11: 标品 | G11: 条 | H11: 线路数 | I11: 外延业务 | L11: 本地SDH电路 | M11: 1221 | N11: 0.06 | O11: 固网及智慧家庭服务-固定电话-固网语音 | P11: 1221 | Q11: 固网及智慧家庭服务-固定电话-固网语音 | R11: 是 | S11: 是 | T11: 需填写速率/带宽 | U11: 无需填写折扣率
A12: JTSJCPDL201913 | B12: 其他固网业务 | C12: JTSJCP02045 | D12: ISDN | E12: 否 | F12: 标品 | G12: 条 | H12: 线路数 | I12: 外延业务 | M12: 1221 | N12: 0.06 | O12: 固网及智慧家庭服务-固定电话-固网语音 | P12: 1221 | Q12: 固网及智慧家庭服务-固定电话-固网语音 | R12: 是 | S12: 是 | T12: 无需填写速率/带宽 | U12: 无需填写折扣率
A13: JTSJCPDL201913 | B13: 其他固网业务 | C13: JTSJCP02053 | D13: 拨号上网 | E13: 否 | F13: 标品 | G13: 条 | H13: 线路数 | I13: 外延业务 | J13: 专线 | L13: ADSL终端接入 | M13: 1312 | N13: 0.06 | O13: 固网及智慧家庭服务-互联网宽带接入-普通宽带-宽带接入收入-其他 | P13: 1309;1310;1311;1312 | Q13: 固网及智慧家庭服务-互联网宽带接入-普通宽带-宽带接入收入-FTTH/O;固网及智慧家庭服务-互联网宽带接入-普通宽带-宽带接入收入-ADSL;固网及智慧家庭服务-互联网宽带接入-普通宽带-宽带接入收入-LAN;固网及智慧家庭服务-互联网宽带接入-普通宽带-宽带接入收入-其他 | R13: 是 | S13: 是 | T13: 需填写速率/带宽 | U13: 无需填写折扣率
A14: JTSJCPDL201913 | B14: 其他固网业务 | C14: JTSJCP02054 | D14: WLAN上网 | E14: 否 | F14: 标品 | G14: 条 | H14: 线路数 | I14: 外延业务 | J14: 专线 | L14: LAN终端接入 | M14: 1312 | N14: 0.06 | O14: 固网及智慧家庭服务-互联网宽带接入-普通宽带-宽带接入收入-其他 | P14: 1309;1310;1311;1312 | Q14: 固网及智慧家庭服务-互联网宽带接入-普通宽带-宽带接入收入-FTTH/O;固网及智慧家庭服务-互联网宽带接入-普通宽带-宽带接入收入-ADSL;固网及智慧家庭服务-互联网宽带接入-普通宽带-宽带接入收入-LAN;固网及智慧家庭服务-互联网宽带接入-普通宽带-宽带接入收入-其他 | R14: 是 | S14: 是 | T14: 需填写速率/带宽 | U14: 无需填写折扣率
A15: JTSJCPDL201913 | B15: 其他固网业务 | C15: JTSJCP02072 | D15: 设备租赁 | E15: 否 | F15: 设备 | G15: 台 | H15: 设备数 | I15: 外延业务 | M15: 1414 | N15: 0.06 | O15: 固网及智慧家庭服务-其他固网通信服务-固网通信网络资源服务收入-固网其他网络资源服务收入 | P15: 1414 | Q15: 固网及智慧家庭服务-其他固网通信服务-固网通信网络资源服务收入-固网其他网络资源服务收入 | R15: 否 | S15: 是 | T15: 无需填写速率/带宽 | U15: 无需填写折扣率
A16: JTSJCPDL201913 | B16: 其他固网业务 | C16: JTSJCP02073 | D16: 通信管道出租 | E16: 否 | F16: 标品 | G16: 条 | H16: 线路数 | I16: 外延业务 | J16: 电路 | M16: 1414 | N16: 0.06 | O16: 固网及智慧家庭服务-其他固网通信服务-固网通信网络资源服务收入-固网其他网络资源服务收入 | P16: 1414;3109; | Q16: 固网及智慧家庭服务-其他固网通信服务-固网通信网络资源服务收入-固网其他网络资源服务收入;产业数字化-资源型服务-组网专线-项目型组网专线-普通组网专线-国际及港澳台网元业务 | R16: 是 | S16: 是 | T16: 无需填写速率/带宽 | U16: 无需填写折扣率
A17: JTSJCPDL201913 | B17: 其他固网业务 | C17: JTSJCP02077 | D17: SI结算支出 | E17: 是 | F17: 其他 | G17: - | H17: - | I17: 行业应用 | J17: ICT | M17: 1616 | N17: 0.06 | O17: 产业数字化-ICT业务-行业平台及应用-通用信息化标品-协同通信 | P17: 1616 | Q17: 产业数字化-ICT业务-行业平台及应用-通用信息化标品-协同通信 | R17: 否 | S17: 是 | T17: 无需填写速率/带宽 | U17: 无需填写折扣率
A18: JTSJCPDL201913 | B18: 其他固网业务 | C18: JTSJCP02079 | D18: 固网其他业务 | E18: 否 | F18: 其他 | G18: - | H18: - | I18: 外延业务 | M18: 1738 | N18: 0.06 | O18: 其他-固网其他 | P18: 1738 | Q18: 其他-固网其他 | R18: 否 | S18: 是 | T18: 无需填写速率/带宽 | U18: 无需填写折扣率
A19: JTSJCPDL201913 | B19: 其他固网业务 | C19: JTSJCP02040 | D19: 爱wifi | E19: 否 | F19: 标品 | G19: 个 | H19: 热点数 | I19: 外延业务 | M19: 2735 | N19: 0.06 | O19: 固网及智慧家庭服务-固定电话-固网增值业务-其他-CP/SP结算支出 | P19: 2735 | Q19: 固网及智慧家庭服务-固定电话-固网增值业务-其他-CP/SP结算支出 | R19: 是 | S19: 是 | T19: 无需填写速率/带宽 | U19: 无需填写折扣率
A20: JTSJCPDL201912 | B20: 增值业务 | C20: JTSJCP02056 | D20: 国内4008电话 | E20: 否 | F20: 标品 | G20: 个 | H20: 号码数 | I20: 外延业务 | M20: 1221 | N20: 0.06 | O20: 固网及智慧家庭服务-固定电话-固网语音 | P20: 1221 | Q20: 固网及智慧家庭服务-固定电话-固网语音 | R20: 是 | S20: 是 | T20: 无需填写速率/带宽 | U20: 无需填写折扣率
A21: JTSJCPDL201912 | B21: 增值业务 | C21: JTSJCP03001 | D21: 行业彩信 | E21: 否 | F21: 标品 | G21: 个 | H21: 短号码数量 | I21: 外延业务 | M21: 1249 | N21: 0.06 | O21: 固网及智慧家庭服务-固定电话-固网增值业务 | P21: 1249 | Q21: 固网及智慧家庭服务-固定电话-固网增值业务 | R21: 是 | S21: 是 | T21: 无需填写速率/带宽 | U21: 无需填写折扣率
A22: JTSJCPDL201912 | B22: 增值业务 | C22: JTSJCP03002 | D22: 行业短信-普通短信 | E22: 否 | F22: 标品 | G22: 个 | H22: 短号码数量 | I22: 外延业务 | M22: 1249 | N22: 0.06 | O22: 固网及智慧家庭服务-固定电话-固网增值业务 | P22: 1249 | Q22: 固网及智慧家庭服务-固定电话-固网增值业务 | R22: 是 | S22: 是 | T22: 无需填写速率/带宽 | U22: 无需填写折扣率
A23: JTSJCPDL201912 | B23: 增值业务 | C23: JTSJCP01002 | D23: 总机服务 | E23: 否 | F23: 标品 | G23: 户 | H23: 开通功能的用户数 | I23: 外延业务 | M23: 1289 | N23: 0.06 | O23: 固网及智慧家庭服务-固定电话-企业总机-收入（大收） | P23: 1289 | Q23: 固网及智慧家庭服务-固定电话-企业总机-收入（大收） | R23: 是 | S23: 是 | T23: 无需填写速率/带宽 | U23: 无需填写折扣率
A24: JTSJCPDL201912 | B24: 增值业务 | C24: JTSJCP01046 | D24: 无线VPDN | E24: 是 | F24: 标品 | G24: 户 | H24: 开通功能的用户数 | I24: 行业应用 -250115改：外延业务 | J24: ICT-250115改：删除产品类别 | M24: 1197 | N24: 0.06 | O24: 移动通信服务-其他移动通信服务-无线宽带收入 | P24: 1197 | Q24: 移动通信服务-其他移动通信服务-无线宽带收入 | R24: 是 | S24: 是 | T24: 无需填写速率/带宽 | U24: 无需填写折扣率
A25: JTSJCPDL201912 | B25: 增值业务 | C25: JTSJCP02058 | D25: 天翼高清（集约） | E25: 否 | F25: 标品 | G25: 台 | H25: 天翼高清的台数 | I25: 外延业务 | M25: 2735 | N25: 0.06 | O25: 固网及智慧家庭服务-固定电话-固网增值业务-其他-CP/SP结算支出 | P25: 2735 | Q25: 固网及智慧家庭服务-固定电话-固网增值业务-其他-CP/SP结算支出 | R25: 是 | S25: 是 | T25: 无需填写速率/带宽 | U25: 无需填写折扣率
A26: JTSJCPDL201912 | B26: 增值业务 | C26: JTSJCP03004 | D26: 800电话 | E26: 否 | F26: 标品 | G26: G | H26: 包含的流量数 | I26: 外延业务 | M26: 1197 | N26: 0.06 | O26: 移动通信服务-其他移动通信服务-无线宽带收入 | P26: 1197 | Q26: 移动通信服务-其他移动通信服务-无线宽带收入 | R26: 是 | S26: 是 | T26: 无需填写速率/带宽 | U26: 无需填写折扣率
A27: JTSJCPDL201912 | B27: 增值业务 | C27: JTSJCP02219 | D27: 行业短信-富媒体短信 | E27: 是 | F27: 标品 | I27: 外延业务 | J27: ICT | M27: 2943 | N27: 0.06 | O27: 移动通信服务-移动信息化应用-个人云产品-天翼云盘-基础功能费 | P27: 2943;2944 | Q27: 移动通信服务-移动信息化应用-个人云产品-天翼云盘-基础功能费;移动通信服务-移动信息化应用-个人云产品-天翼云盘-会员服务费 | R27: 是 | S27: 是 | T27: 无需填写速率/带宽 | U27: 无需填写折扣率
A28: JTSJCPDL201912 | B28: 增值业务 | C28: JTSJCP02220 | D28: 行业短信-秒达短信 | E28: 是 | F28: 标品 | I28: 外延业务 | J28: ICT | M28: 2943 | N28: 0.06 | O28: 移动通信服务-移动信息化应用-个人云产品-天翼云盘-基础功能费 | P28: 2943;2944 | Q28: 移动通信服务-移动信息化应用-个人云产品-天翼云盘-基础功能费;移动通信服务-移动信息化应用-个人云产品-天翼云盘-会员服务费 | R28: 是 | S28: 是 | T28: 无需填写速率/带宽 | U28: 无需填写折扣率
A29: JTSJCPDL201912 | B29: 增值业务 | C29: JTSJCP02221 | D29: 行业短信-智能短信 | E29: 是 | F29: 标品 | I29: 外延业务 | J29: ICT | M29: 2943 | N29: 0.06 | O29: 移动通信服务-移动信息化应用-个人云产品-天翼云盘-基础功能费 | P29: 2943;2944 | Q29: 移动通信服务-移动信息化应用-个人云产品-天翼云盘-基础功能费;移动通信服务-移动信息化应用-个人云产品-天翼云盘-会员服务费 | R29: 是 | S29: 是 | T29: 无需填写速率/带宽 | U29: 无需填写折扣率
A30: JTSJCPDL201911 | B30: 基础移动业务 | C30: JTSJCP01001 | D30: 4G（LTE）上网 | E30: 否 | F30: 标品 | G30: 户 | H30: 拉动移动入网用户数 | I30: 外延业务 | K30: 040229 | L30: 移动业务户均成本 | M30: 1005 | N30: 0.06 | O30: 移动通信服务-移动语音-语音收入 | P30: 1005 | Q30: 移动通信服务-移动语音-语音收入 | R30: 是 | S30: 是 | T30: 无需填写速率/带宽 | U30: 无需填写折扣率
A31: JTSJCPDL201910 | B31: 卫星业务 | C31: JTSJCP01051 | D31: 卫星移动通信业务-语音 | E31: 否 | F31: 标品 | G31: 户 | H31: 拉动移动入网用户数 | I31: 外延业务 | J31: 专线 | M31: 1005 | N31: 0.06 | O31: 移动通信服务-移动语音-语音收入 | P31: 1005 | Q31: 移动通信服务-移动语音-语音收入 | R31: 是 | T31: 无需填写速率/带宽 | U31: 无需填写折扣率
A32: JTSJCPDL201910 | B32: 卫星业务 | C32: JTSJCP02090 | D32: 卫星宽带带宽型-国内 | E32: 否 | F32: 标品 | G32: 条 | H32: 线路数 | I32: 外延业务 | J32: 专线 | L32: 专线接入成本 | M32: 1301 | N32: 0.06 | O32: 固网及智慧家庭服务-互联网宽带接入-卫星宽带-卫星宽带服务 | P32: 1301;1302; | Q32: 固网及智慧家庭服务-互联网宽带接入-卫星宽带-卫星宽带服务;固网及智慧家庭服务-互联网宽带接入-卫星宽带-卫星资源服务 | R32: 是 | S32: 是 | T32: 需填写速率/带宽 | U32: 无需填写折扣率
A33: JTSJCPDL201910 | B33: 卫星业务 | C33: JTSJCP02051 | D33: 卫星宽带流量型（企业版） | E33: 否 | F33: 标品 | G33: 条 | H33: 线路数 | I33: 外延业务 | J33: 电路 | M33: 1301 | N33: 0.06 | O33: 固网及智慧家庭服务-互联网宽带接入-卫星宽带-卫星宽带服务 | P33: 1301;1302; | Q33: 固网及智慧家庭服务-互联网宽带接入-卫星宽带-卫星宽带服务;固网及智慧家庭服务-互联网宽带接入-卫星宽带-卫星资源服务 | R33: 是 | S33: 是 | T33: 无需填写速率/带宽 | U33: 无需填写折扣率
A34: JTSJCPDL201910 | B34: 卫星业务 | C34: JTSJCP02052 | D34: 卫星宽带带宽型-国际 | E34: 否 | F34: 标品 | G34: 条 | H34: 线路数 | I34: 外延业务 | J34: 专线 | L34: 专线接入成本 | M34: 1301 | N34: 0.06 | O34: 固网及智慧家庭服务-互联网宽带接入-卫星宽带-卫星宽带服务 | P34: 1301;1302; | Q34: 固网及智慧家庭服务-互联网宽带接入-卫星宽带-卫星宽带服务;固网及智慧家庭服务-互联网宽带接入-卫星宽带-卫星资源服务 | R34: 是 | S34: 是 | T34: 需填写速率/带宽 | U34: 无需填写折扣率
A35: JTSJCPDL201910 | B35: 卫星业务 | C35: JTSJCP03108 | D35: 手机直连卫星 | E35: 否 | F35: 标品 | I35: 卫星 | R35: 是 | T35: 无需填写速率/带宽 | U35: 无需填写折扣率
A36: JTSJCPDL201909 | B36: 专线业务 | C36: JTSJCP02042 | D36: 互联网专线-500M以下 | E36: 否 | F36: 标品 | G36: 条 | H36: 线路数 | I36: 外延业务 | J36: 专线 | L36: 专线接入成本 | M36: 1320 | N36: 0.06 | O36: 固网及智慧家庭服务-互联网宽带接入-互联网专线-普通国内互联网专线收入-FTTH/O | P36: 1306;1307;1320;1321;1322;1323;1326;1329;1330;1331;2557 | Q36: 固网及智慧家庭服务-互联网宽带接入-普通宽带-装移机收入;固网及智慧家庭服务-互联网宽带接入-普通宽带-业务调测费;固网及智慧家庭服务-互联网宽带接入-互联网专线-普通国内互联网专线收入-FTTH/O;固网及智慧家庭服务-互联网宽带接入-互联网专线-普通国内互联网专线收入-ADSL;固网及智慧家庭服务-互联网宽带接入-互联网专线-普通国内互联网专线收入-LAN;固网及智慧家庭服务-互联网宽带接入-互联网专线-普通国内互联网专线收入-光纤直驱;固网及智慧家庭服务-互联网宽带接入-互联网专线-普通国内互联网专线收入-光纤直驱;固网及智慧家庭服务-互联网宽带接入-互联网专线-互联网专线安全服务（云堤）-DDoS攻击防护服务（互联网）;固网及智慧家庭服务-互联网宽带接入-互联网专线-互联网专线安全服务（云堤）-云镜;固网及智慧家庭服务-互联网宽带接入-互联网专线-商务专线;固网及智慧家庭服务-互联网宽带接入-互联网专线-国际精品专线;固网及智慧家庭服务-互联网宽带接入-其他互联网宽带接入业务-其他 | R36: 是 | S36: 是 | T36: 需填写速率/带宽 | U36: 无需填写折扣率
A37: JTSJCPDL201909 | B37: 专线业务 | C37: JTSJCP02108 | D37: 互联网专线-500M及以上 | E37: 否 | F37: 标品 | G37: 条 | H37: 线路数 | I37: 外延业务 | J37: 专线 | L37: 专线接入成本 | M37: 1320 | N37: 0.06 | O37: 固网及智慧家庭服务-互联网宽带接入-互联网专线-普通国内互联网专线收入-FTTH/O | P37: 1306;1307;1320;1321;1322;1323;1326;1329;1330;1331;2557 | Q37: 固网及智慧家庭服务-互联网宽带接入-普通宽带-装移机收入;固网及智慧家庭服务-互联网宽带接入-普通宽带-业务调测费;固网及智慧家庭服务-互联网宽带接入-互联网专线-普通国内互联网专线收入-FTTH/O;固网及智慧家庭服务-互联网宽带接入-互联网专线-普通国内互联网专线收入-ADSL;固网及智慧家庭服务-互联网宽带接入-互联网专线-普通国内互联网专线收入-LAN;固网及智慧家庭服务-互联网宽带接入-互联网专线-普通国内互联网专线收入-光纤直驱;固网及智慧家庭服务-互联网宽带接入-互联网专线-普通国内互联网专线收入-光纤直驱;固网及智慧家庭服务-互联网宽带接入-互联网专线-互联网专线安全服务（云堤）-DDoS攻击防护服务（互联网）;固网及智慧家庭服务-互联网宽带接入-互联网专线-互联网专线安全服务（云堤）-云镜;固网及智慧家庭服务-互联网宽带接入-互联网专线-商务专线;固网及智慧家庭服务-互联网宽带接入-互联网专线-国际精品专线;固网及智慧家庭服务-互联网宽带接入-其他互联网宽带接入业务-其他 | R37: 是 | S37: 是 | T37: 需填写速率/带宽 | U37: 无需填写折扣率
A38: JTSJCPDL201909 | B38: 专线业务 | C38: JTSJCP02089 | D38: 互联网国际精品专线-500M以下 | E38: 否 | F38: 标品 | G38: 条 | H38: 线路数 | I38: 外延业务 | J38: 专线 | L38: 专线接入成本 | M38: 1331 | N38: 0.06 | O38: 固网及智慧家庭服务-互联网宽带接入-互联网专线-国际精品专线 | P38: 1331 | Q38: 固网及智慧家庭服务-互联网宽带接入-互联网专线-国际精品专线 | R38: 是 | S38: 是 | T38: 需填写速率/带宽 | U38: 无需填写折扣率
A39: JTSJCPDL201909 | B39: 专线业务 | C39: JTSJCP02109 | D39: 互联网国际精品专线-500M及以上 | E39: 否 | F39: 标品 | G39: 条 | H39: 线路数 | I39: 外延业务 | J39: 专线 | L39: 专线接入成本 | M39: 1331 | N39: 0.06 | O39: 固网及智慧家庭服务-互联网宽带接入-互联网专线-国际精品专线 | P39: 1331 | Q39: 固网及智慧家庭服务-互联网宽带接入-互联网专线-国际精品专线 | R39: 是 | S39: 是 | T39: 需填写速率/带宽 | U39: 无需填写折扣率
A40: JTSJCPDL201909 | B40: 专线业务 | C40: JTSJCP02088 | D40: 商务专线 | E40: 否 | F40: 标品 | G40: 条 | H40: 线路数 | I40: 外延业务 | J40: 专线 | L40: 商务光纤接入 | M40: 1330 | N40: 0.06 | O40: 固网及智慧家庭服务-互联网宽带接入-互联网专线-商务专线 | P40: 1330 | Q40: 固网及智慧家庭服务-互联网宽带接入-互联网专线-商务专线 | R40: 是 | S40: 是 | T40: 需填写速率/带宽 | U40: 无需填写折扣率
A41: JTSJCPDL201908 | B41: 电路业务 | C41: JTSJCP02041 | D41: IP虚拟专网 | E41: 否 | F41: 标品 | G41: 条 | H41: 线路数 | I41: 外延业务 | J41: 电路 | L41: 专线接入成本 | M41: 3071(标）、3104(项) | N41: 0.09 | O41: 产业数字化-资源型服务-组网专线-标品型-普通组网专线-普通组网专线-IP虚拟专网-大陆境内 | P41: 3071;3073;3074 | Q41: 产业数字化-资源型服务-组网专线-标品型-普通组网专线-IP虚拟专网-大陆境内;产业数字化-资源型服务-组网专线-标品型-普通组网专线-IP虚拟专网-国际及港澳台-境内客户;产业数字化-资源型服务-组网专线-标品型-普通组网专线-IP虚拟专网-国际及港澳台-境外客户 | R41: 是 | S41: 是 | T41: 需填写速率/带宽 | U41: 无需填写折扣率
A42: JTSJCPDL201908 | B42: 电路业务 | C42: JTSJCP02048 | D42: 数字电路(SDH)-本地电路 | E42: 否 | F42: 标品 | G42: 条 | H42: 线路数 | I42: 外延业务 | J42: 电路 | L42: 省际长途SDH电路 | M42: 3059(标）、3092(项) | N42: 0.09 | O42: 产业数字化-资源型服务-组网专线-标品型-普通组网专线-普通组网专线-传输专线（SDH/MSTP/波分/ROADM）-大陆境内-长途 | P42: 3059 | Q42: 产业数字化-资源型服务-组网专线-标品型-普通组网专线-传输专线（SDH/MSTP/波分/ROADM）-大陆境内-长途 | R42: 是 | S42: 是 | T42: 需填写速率/带宽 | U42: 无需填写折扣率
A43: JTSJCPDL201908 | B43: 电路业务 | C43: JTSJCP02102 | D43: 数字电路(SDH)-省内长途 | E43: 否 | F43: 标品 | G43: 条 | H43: 线路数 | I43: 外延业务 | J43: 电路 | L43: 省内长途SDH电路 | M43: 3059(标）、3092(项) | N43: 0.09 | O43: 产业数字化-资源型服务-组网专线-标品型-普通组网专线-普通组网专线-传输专线（SDH/MSTP/波分/ROADM）-大陆境内-长途 | P43: 3059 | Q43: 产业数字化-资源型服务-组网专线-标品型-普通组网专线-传输专线（SDH/MSTP/波分/ROADM）-大陆境内-长途 | R43: 是 | S43: 是 | T43: 需填写速率/带宽 | U43: 无需填写折扣率
A44: JTSJCPDL201908 | B44: 电路业务 | C44: JTSJCP02103 | D44: 数字电路(SDH)-省际长途 | E44: 否 | F44: 标品 | G44: 条 | H44: 线路数 | I44: 外延业务 | J44: 电路 | L44: 本地SDH电路 | M44: 3058(标）、3091(项) | N44: 0.09 | O44: 产业数字化-资源型服务-组网专线-标品型-普通组网专线-普通组网专线-传输专线（SDH/MSTP/波分/ROADM）-大陆境内-本地 | P44: 3058 | Q44: 产业数字化-资源型服务-组网专线-标品型-普通组网专线-传输专线（SDH/MSTP/波分/ROADM）-大陆境内-本地 | R44: 是 | S44: 是 | T44: 需填写速率/带宽 | U44: 无需填写折扣率
A45: JTSJCPDL201908 | B45: 电路业务 | C45: JTSJCP02049 | D45: MSTP-本地电路 | E45: 否 | F45: 标品 | G45: 条 | H45: 线路数 | I45: 外延业务 | J45: 电路 | L45: 省际长途SDH电路 | M45: 3059(标）、3092(项) | N45: 0.09 | O45: 产业数字化-资源型服务-组网专线-标品型-普通组网专线-普通组网专线-传输专线（SDH/MSTP/波分/ROADM）-大陆境内-长途 | P45: 3059 | Q45: 产业数字化-资源型服务-组网专线-标品型-普通组网专线-传输专线（SDH/MSTP/波分/ROADM）-大陆境内-长途 | R45: 是 | S45: 是 | T45: 需填写速率/带宽 | U45: 无需填写折扣率
A46: JTSJCPDL201908 | B46: 电路业务 | C46: JTSJCP02104 | D46: MSTP-省内长途 | E46: 否 | F46: 标品 | G46: 条 | H46: 线路数 | I46: 外延业务 | J46: 电路 | L46: 省内长途SDH电路 | M46: 3059(标）、3092(项) | N46: 0.09 | O46: 产业数字化-资源型服务-组网专线-标品型-普通组网专线-普通组网专线-传输专线（SDH/MSTP/波分/ROADM）-大陆境内-长途 | P46: 3059 | Q46: 产业数字化-资源型服务-组网专线-标品型-普通组网专线-传输专线（SDH/MSTP/波分/ROADM）-大陆境内-长途 | R46: 是 | S46: 是 | T46: 需填写速率/带宽 | U46: 无需填写折扣率
A47: JTSJCPDL201908 | B47: 电路业务 | C47: JTSJCP02105 | D47: MSTP-省际长途 | E47: 否 | F47: 标品 | G47: 条 | H47: 线路数 | I47: 外延业务 | J47: 电路 | L47: 本地SDH电路 | M47: 3058(标）、3091(项) | N47: 0.09 | O47: 产业数字化-资源型服务-组网专线-标品型-普通组网专线-普通组网专线-传输专线（SDH/MSTP/波分/ROADM）-大陆境内-本地 | P47: 3058 | Q47: 产业数字化-资源型服务-组网专线-标品型-普通组网专线-传输专线（SDH/MSTP/波分/ROADM）-大陆境内-本地 | R47: 是 | S47: 是 | T47: 需填写速率/带宽 | U47: 无需填写折扣率
A48: JTSJCPDL201908 | B48: 电路业务 | C48: JTSJCP02070 | D48: 以太专线 | E48: 否 | F48: 标品 | G48: 条 | H48: 线路数 | I48: 外延业务 | J48: 电路 | L48: 专线接入成本 | M48: 3065(标）、3098(项) | N48: 0.09 | O48: 产业数字化-资源型服务-组网专线-标品型-普通组网专线-普通组网专线-以太专线-大陆境内-本地 | P48: 3065;3066 | Q48: 产业数字化-资源型服务-组网专线-标品型-普通组网专线-以太专线-大陆境内-本地;产业数字化-资源型服务-组网专线-标品型-普通组网专线-以太专线-大陆境内-长途 | R48: 是 | S48: 是 | T48: 需填写速率/带宽 | U48: 无需填写折扣率
A49: JTSJCPDL201908 | B49: 电路业务 | C49: JTSJCP02111 | D49: 数字电路(SDH)-国际港澳台电路 | E49: 否 | F49: 标品 | G49: 条 | H49: 线路数 | I49: 外延业务 | J49: 电路 | L49: 省际长途SDH电路 | M49: 3061(标）、3094(项) | N49: 0.09 | O49: 产业数字化-资源型服务-组网专线-标品型-普通组网专线-普通组网专线-传输专线（SDH/MSTP/波分/ROADM）-国际及港澳台-境内客户 | P49: 3061 | Q49: 产业数字化-资源型服务-组网专线-标品型-普通组网专线-传输专线（SDH/MSTP/波分/ROADM）-国际及港澳台-境内客户 | R49: 是 | S49: 是 | T49: 需填写速率/带宽 | U49: 无需填写折扣率
A50: JTSJCPDL201908 | B50: 电路业务 | C50: JTSJCP02112 | D50: MSTP-国际港澳台电路 | E50: 否 | F50: 标品 | G50: 条 | H50: 线路数 | I50: 外延业务 | J50: 电路 | L50: 省际长途SDH电路 | M50: 3061(标）、3094(项) | N50: 0.09 | O50: 产业数字化-资源型服务-组网专线-标品型-普通组网专线-普通组网专线-传输专线（SDH/MSTP/波分/ROADM）-国际及港澳台-境内客户 | P50: 3061 | Q50: 产业数字化-资源型服务-组网专线-标品型-普通组网专线-传输专线（SDH/MSTP/波分/ROADM）-国际及港澳台-境内客户 | R50: 是 | S50: 是 | T50: 需填写速率/带宽 | U50: 无需填写折扣率
A51: JTSJCPDL201908 | B51: 电路业务 | C51: JTSJCP02114 | D51: 医疗专网（统筹省级） | E51: 否 | F51: 标品 | G51: 条 | H51: 线路数 | I51: 外延业务 | J51: 电路 | L51: 专线接入成本 | M51: 3077(标）、3110(项) | N51: 0.09 | O51: 产业数字化-资源型服务-组网专线-标品型-普通组网专线-普通组网专线-其他 | P51: 3077 | Q51: 产业数字化-资源型服务-组网专线-标品型-普通组网专线-其他 | R51: 是 | S51: 是 | T51: 需填写速率/带宽 | U51: 无需填写折扣率
A52: JTSJCPDL201908 | B52: 电路业务 | C52: JTSJCP02115 | D52: 精品专线（OTN）-省际长途 | E52: 否 | F52: 标品 | G52: 条 | H52: 线路数 | I52: 外延业务 | J52: 电路 | L52: 省际长途SDH电路 | M52: 3030(标）、3085(项) | N52: 0.09 | O52: 产业数字化-资源型服务-组网专线-标品型-普通组网专线-普通组网专线-OTN精品专线-大陆境内-长途 | P52: 3030 | Q52: 产业数字化-资源型服务-组网专线-标品型-普通组网专线-OTN精品专线-大陆境内-长途 | R52: 是 | S52: 是 | T52: 需填写速率/带宽 | U52: 无需填写折扣率
A53: JTSJCPDL201908 | B53: 电路业务 | C53: JTSJCP02116 | D53: 精品专线（OTN）-省内长途 | E53: 否 | F53: 标品 | I53: 外延业务 | J53: 电路 | L53: 省内长途SDH电路 | M53: 3030(标）、3085(项) | N53: 0.09 | O53: 产业数字化-资源型服务-组网专线-标品型-普通组网专线-普通组网专线-OTN精品专线-大陆境内-长途 | P53: 3030 | Q53: 产业数字化-资源型服务-组网专线-标品型-普通组网专线-OTN精品专线-大陆境内-长途 | R53: 是 | S53: 是 | T53: 需填写速率/带宽 | U53: 无需填写折扣率
A54: JTSJCPDL201908 | B54: 电路业务 | C54: JTSJCP02117 | D54: 精品专线（OTN）-本地电路 | E54: 否 | F54: 标品 | I54: 外延业务 | J54: 电路 | L54: 本地SDH电路 | M54: 3029(标）、3084(项) | N54: 0.09 | O54: 产业数字化-资源型服务-组网专线-标品型-普通组网专线-普通组网专线-OTN精品专线-大陆境内-本地 | P54: 3029 | Q54: 产业数字化-资源型服务-组网专线-标品型-普通组网专线-OTN精品专线-大陆境内-本地 | R54: 是 | S54: 是 | T54: 需填写速率/带宽 | U54: 无需填写折扣率
A55: JTSJCPDL201908 | B55: 电路业务 | C55: JTSJCP04073 | D55: 云专网3.0 | E55: 否 | F55: 标品 | I55: 外延业务 | M55: 1965 | N55: 0.09 | O55: 产业数字化-资源型服务-组网专线-项目型组网专线-云组网专线-资源池接入专线-云专网（含FIRST教育/医疗/视频专网等） | P55: 1965 | Q55: 产业数字化-资源型服务-组网专线-项目型组网专线-云组网专线-资源池接入专线-云专网（含FIRST教育/医疗/视频专网等） | R55: 是 | S55: 是 | T55: 需填写速率/带宽 | U55: 无需填写折扣率
A56: JTSJCPDL201907 | B56: 物联网业务 | C56: JTSJCP04001 | D56: 物联网语音 | E56: 否 | F56: 标品 | G56: 户 | H56: 拉动移动入网用户数 | I56: 物联网 | J56: 物联网 | M56: 1714 | N56: 0.09 | O56: 产业数字化-资源型服务-物联网-标品型物联网-连接服务-语音 | P56: 1714 | Q56: 产业数字化-资源型服务-物联网-标品型物联网-连接服务-语音 | R56: 是 | S56: 是 | T56: 无需填写速率/带宽 | U56: 无需填写折扣率
A57: JTSJCPDL201907 | B57: 物联网业务 | C57: JTSJCP04002 | D57: 物联网流量 | E57: 否 | F57: 标品 | G57: 户 | H57: 拉动移动入网用户数 | I57: 物联网 | J57: 物联网 | M57: 1716 | N57: 0.06 | O57: 产业数字化-资源型服务-物联网-标品型物联网-连接服务-流量-定向流量 | P57: 1716 | Q57: 产业数字化-资源型服务-物联网-标品型物联网-连接服务-流量-定向流量 | R57: 是 | S57: 是 | T57: 无需填写速率/带宽 | U57: 需填写折扣率
A58: JTSJCPDL201907 | B58: 物联网业务 | C58: JTSJCP04003 | D58: 物联网短信 | E58: 否 | F58: 标品 | G58: 户 | H58: 拉动移动入网用户数 | I58: 物联网 | J58: 物联网 | M58: 1719 | N58: 0.06 | O58: 产业数字化-资源型服务-物联网-标品型物联网-连接服务-短信 | P58: 1719 | Q58: 产业数字化-资源型服务-物联网-标品型物联网-连接服务-短信 | R58: 是 | S58: 是 | T58: 无需填写速率/带宽 | U58: 无需填写折扣率
A59: JTSJCPDL201907 | B59: 物联网业务 | C59: JTSJCP04004 | D59: 物联网基础能力增值 | E59: 否 | F59: 标品 | G59: 户 | H59: 拉动移动入网用户数 | I59: 物联网 | J59: 物联网 | M59: 1720 | N59: 0.06 | O59: 产业数字化-资源型服务-物联网-标品型物联网-连接服务-增值 | P59: 1720 | Q59: 产业数字化-资源型服务-物联网-标品型物联网-连接服务-增值 | R59: 是 | S59: 是 | T59: 无需填写速率/带宽 | U59: 无需填写折扣率
A60: JTSJCPDL201907 | B60: 物联网业务 | C60: JTSJCP02218 | D60: 物联网开放平台 | E60: 是 | F60: 标品 | I60: 物联网 | J60: ICT | M60: 3113(标）、3123(项) | N60: 0.06 | O60: 产业数字化-资源型服务-物联网-标品型物联网-应用服务-平台应用 | P60: 3113 | Q60: 产业数字化-资源型服务-物联网-标品型物联网-应用服务-平台应用 | R60: 是 | S60: 是 | T60: 无需填写速率/带宽 | U60: 无需填写折扣率
A61: JTSJCPDL201907 | B61: 物联网业务 | C61: JTSJCP04005 | D61: 物联网应用 | E61: 否 | F61: 标品 | G61: 户 | H61: 拉动移动入网用户数 | I61: 物联网 | J61: 物联网 | M61: 3119(标）、3129(项) | N61: 0.06 | O61: 产业数字化-资源型服务-物联网-标品型物联网-应用服务-行业应用-其他 | P61: 3119 | Q61: 产业数字化-资源型服务-物联网-标品型物联网-应用服务-行业应用-其他 | R61: 是 | S61: 是 | T61: 无需填写速率/带宽 | U61: 无需填写折扣率
A62: JTSJCPDL201907 | B62: 物联网业务 | C62: JTSJCP01047 | D62: M2M | E62: 是 | F62: 其他 | G62: 户 | H62: 开通功能的用户数 | I62: 行业应用 | J62: ICT | K62: 040601 | L62: 物联网平台 | M62: 2914 | N62: 0.06 | O62: 产业数字化-ICT业务-集成-集成服务-物联网集成 | P62: 2914 | Q62: 产业数字化-ICT业务-集成-集成服务-物联网集成 | R62: 否 | S62: 是 | T62: 无需填写速率/带宽 | U62: 无需填写折扣率
A63: JTSJCPDL201907 | B63: 物联网业务 | C63: JTSJCP04009 | D63: 城市感知平台 | E63: 是 | F63: 能力 | G63: 户 | H63: 开通功能的用户数 | I63: 物联网 | J63: ICT | M63: 2914 | N63: 0.06 | O63: 产业数字化-ICT业务-集成-集成服务-物联网集成 | P63: 2914 | Q63: 产业数字化-ICT业务-集成-集成服务-物联网集成 | R63: 否 | S63: 是 | T63: 无需填写速率/带宽 | U63: 无需填写折扣率
A64: JTSJCPDL201906 | B64: ICT-其它 | C64: JTSJCP02066 | D64: 其他ICT业务 | E64: 是 | F64: 能力 | G64: - | H64: - | I64: 集成服务 | J64: ICT | M64: 1708 | N64: 0.06 | O64: 产业数字化-ICT业务-集成-天翼智维-客户云网托管服务 | P64: 1708 | Q64: 产业数字化-ICT业务-集成-天翼智维-客户云网托管服务 | R64: 否 | S64: 否 | T64: 无需填写速率/带宽 | U64: 无需填写折扣率
A65: JTSJCPDL201906 | B65: ICT-其它 | C65: JTSJCP03006 | D65: 代收代付 | E65: 否 | F65: 其他 | G65: - | H65: - | M65: 9999 | N65: 0.13 | O65: 代收代付 | P65: 9999 | Q65: 代收代付 | R65: 否 | S65: 否 | T65: 无需填写速率/带宽 | U65: 无需填写折扣率
A66: JTSJCPDL201906 | B66: ICT-其它 | C66: JTSJCP01050 | D66: 移动ICT服务 | E66: 是 | F66: 能力 | G66: - | H66: - | I66: 集成服务 | J66: ICT | M66: 2408 | N66: 0.06 | O66: 产业数字化-ICT业务-行业平台及应用-行业数字平台 | P66: 2408 | Q66: 产业数字化-ICT业务-行业平台及应用-行业数字平台 | R66: 否 | S66: 否 | T66: 无需填写速率/带宽 | U66: 无需填写折扣率
A67: JTSJCPDL201905 | B67: ICT-行业应用 | C67: JTSJCP02080 | D67: 智慧企业 | E67: 是 | F67: 能力 | G67: - | H67: - | I67: 行业应用 | J67: ICT | M67: 2408 | N67: 0.06 | O67: 产业数字化-ICT业务-行业平台及应用-行业数字平台 | P67: 2408 | Q67: 产业数字化-ICT业务-行业平台及应用-行业数字平台 | R67: 否 | S67: 否 | T67: 无需填写速率/带宽 | U67: 无需填写折扣率
A68: JTSJCPDL201905 | B68: ICT-行业应用 | C68: JTSJCP01003 | D68: 加密通信 | E68: 是 | F68: 标品 | G68: 户 | H68: 开通功能的用户数 | I68: 行业应用 | J68: ICT | M68: 1637 | N68: 0.06 | O68: 产业数字化-ICT业务-行业平台及应用-通用信息化标品-加密通信 | P68: 1637 | Q68: 产业数字化-ICT业务-行业平台及应用-通用信息化标品-加密通信 | R68: 是 | S68: 是 | T68: 无需填写速率/带宽 | U68: 无需填写折扣率
A69: JTSJCPDL201905 | B69: ICT-行业应用 | C69: JTSJCP01016 | D69: 安全办公 | E69: 是 | F69: 标品 | G69: 户 | H69: 开通功能的用户数 | I69: 行业应用 | J69: ICT | K69: 040901 | L69: 综合办公平台 | M69: 1634 | N69: 0.06 | O69: 产业数字化-ICT业务-行业平台及应用-通用信息化标品-安全办公 | P69: 1634 | Q69: 产业数字化-ICT业务-行业平台及应用-通用信息化标品-安全办公 | R69: 是 | S69: 是 | T69: 无需填写速率/带宽 | U69: 无需填写折扣率
A70: JTSJCPDL201905 | B70: ICT-行业应用 | C70: JTSJCP01018 | D70: 外勤助手 | E70: 是 | F70: 标品 | G70: 户 | H70: 开通功能的用户数 | I70: 行业应用 | J70: ICT | K70: 040217 | L70: 行业应用类平台(外勤助手) | M70: 1625 | N70: 0.06 | O70: 产业数字化-ICT业务-行业平台及应用-通用信息化标品-外勤助手 | P70: 1625 | Q70: 产业数字化-ICT业务-行业平台及应用-通用信息化标品-外勤助手 | R70: 是 | S70: 是 | T70: 无需填写速率/带宽 | U70: 无需填写折扣率
A71: JTSJCPDL201905 | B71: ICT-行业应用 | C71: JTSJCP01019 | D71: 天翼对讲 | E71: 是 | F71: 标品 | G71: 户 | H71: 开通功能的用户数 | I71: 行业应用 | J71: ICT | K71: 040401 | L71: 天翼对讲平台 | M71: 1622 | N71: 0.06 | O71: 产业数字化-ICT业务-行业平台及应用-通用信息化标品-天翼对讲 | P71: 1622 | Q71: 产业数字化-ICT业务-行业平台及应用-通用信息化标品-天翼对讲 | R71: 是 | S71: 是 | T71: 无需填写速率/带宽 | U71: 无需填写折扣率
A72: JTSJCPDL201905 | B72: ICT-行业应用 | C72: JTSJCP01020 | D72: 可视化调度 | E72: 是 | F72: 标品 | G72: 户 | H72: 开通功能的用户数 | I72: 行业应用 | J72: ICT | K72: 040401 | L72: 天翼对讲平台 | M72: 1622 | N72: 0.06 | O72: 产业数字化-ICT业务-行业平台及应用-通用信息化标品-天翼对讲 | P72: 1622 | Q72: 产业数字化-ICT业务-行业平台及应用-通用信息化标品-天翼对讲 | R72: 是 | S72: 是 | T72: 无需填写速率/带宽 | U72: 无需填写折扣率
A73: JTSJCPDL201905 | B73: ICT-行业应用 | C73: JTSJCP01021 | D73: 综合办公 | E73: 是 | F73: 标品 | G73: 户 | H73: 开通功能的用户数 | I73: 行业应用 | J73: ICT | K73: 040901 | L73: 综合办公平台 | M73: 1628 | N73: 0.06 | O73: 产业数字化-ICT业务-行业平台及应用-通用信息化标品-综合办公 | P73: 1628 | Q73: 产业数字化-ICT业务-行业平台及应用-通用信息化标品-综合办公 | R73: 是 | S73: 是 | T73: 无需填写速率/带宽 | U73: 无需填写折扣率
A74: JTSJCPDL201905 | B74: ICT-行业应用 | C74: JTSJCP02029 | D74: 新视通（4G版） | E74: 是 | F74: 标品 | G74: 个 | H74: 终端数量 | I74: ICT | J74: ICT | M74: 1653 | N74: 0.06 | O74: 产业数字化-ICT业务-行业平台及应用-通用信息化标品-视频会议 | P74: 1653 | Q74: 产业数字化-ICT业务-行业平台及应用-通用信息化标品-视频会议 | R74: 是 | S74: 是 | T74: 无需填写速率/带宽 | U74: 无需填写折扣率
A75: JTSJCPDL201905 | B75: ICT-行业应用 | C75: JTSJCP02037 | D75: 12345政府服务热线 | E75: 是 | F75: 能力 | G75: 个 | H75: 支持坐席数 | I75: 集成服务 | J75: ICT | M75: 1706 | N75: 0.06 | O75: 产业数字化-ICT业务-行业平台及应用-通用信息化标品-呼叫中心外包服务收入 | P75: 1706 | Q75: 产业数字化-ICT业务-行业平台及应用-通用信息化标品-呼叫中心外包服务收入 | R75: 否 | S75: 是 | T75: 无需填写速率/带宽 | U75: 无需填写折扣率
A76: JTSJCPDL201905 | B76: ICT-行业应用 | C76: JTSJCP02057 | D76: 会易通 | E76: 否 | F76: 标品 | G76: 个 | H76: 虚拟会议室数 | I76: 行业应用 | J76: ICT | M76: 1653 | N76: 0.06 | O76: 产业数字化-ICT业务-行业平台及应用-通用信息化标品-视频会议 | P76: 1653 | Q76: 产业数字化-ICT业务-行业平台及应用-通用信息化标品-视频会议 | R76: 是 | S76: 是 | T76: 无需填写速率/带宽 | U76: 无需填写折扣率
A77: JTSJCPDL201905 | B77: ICT-行业应用 | C77: JTSJCP02065 | D77: 鹰眼舆情 | E77: 是 | F77: 标品 | G77: - | H77: - | I77: 大数据 | J77: ICT | M77: 1678 | N77: 0.06 | O77: 产业数字化-ICT业务-集成-集成服务-安全集成-其他 | P77: 1678 | Q77: 产业数字化-ICT业务-集成-集成服务-安全集成-其他 | R77: 是 | S77: 是 | T77: 无需填写速率/带宽 | U77: 无需填写折扣率
A78: JTSJCPDL201905 | B78: ICT-行业应用 | C78: JTSJCP03005 | D78: 基础定位能力业务-粗定位 | E78: 是 | F78: 标品 | G78: 次 | H78: 用户数 | I78: 行业应用 | J78: ICT | K78: 040101 | L78: 定位服务平台 | M78: 1640 | N78: 0.06 | O78: 产业数字化-ICT业务-行业平台及应用-通用信息化标品-基础定位 | P78: 1640 | Q78: 产业数字化-ICT业务-行业平台及应用-通用信息化标品-基础定位 | R78: 是 | S78: 是 | T78: 无需填写速率/带宽 | U78: 无需填写折扣率
A79: JTSJCPDL201905 | B79: ICT-行业应用 | C79: JTSJCP02206 | D79: 云录音 | E79: 是 | F79: 标品 | I79: 行业应用 | J79: ICT | M79: 1912 | N79: 0.06 | O79: 产业数字化-ICT业务-行业平台及应用-通用信息化标品-智能语音云-云录音 | P79: 1912 | Q79: 产业数字化-ICT业务-行业平台及应用-通用信息化标品-智能语音云-云录音 | R79: 是 | S79: 是 | T79: 无需填写速率/带宽 | U79: 无需填写折扣率
A80: JTSJCPDL201905 | B80: ICT-行业应用 | C80: JTSJCP02207 | D80: 云中继 | E80: 是 | F80: 标品 | I80: 行业应用 | J80: ICT | M80: 1913 | N80: 0.06 | O80: 产业数字化-ICT业务-行业平台及应用-通用信息化标品-智能语音云-云中继 | P80: 1913 | Q80: 产业数字化-ICT业务-行业平台及应用-通用信息化标品-智能语音云-云中继 | R80: 是 | S80: 是 | T80: 无需填写速率/带宽 | U80: 无需填写折扣率
A81: JTSJCPDL201905 | B81: ICT-行业应用 | C81: JTSJCP02208 | D81: 工作号 | E81: 是 | F81: 标品 | I81: 行业应用 | J81: ICT | M81: 1914 | N81: 0.06 | O81: 产业数字化-ICT业务-行业平台及应用-通用信息化标品-智能语音云-工作号 | P81: 1914 | Q81: 产业数字化-ICT业务-行业平台及应用-通用信息化标品-智能语音云-工作号 | R81: 是 | S81: 是 | T81: 无需填写速率/带宽 | U81: 无需填写折扣率
A82: JTSJCPDL201905 | B82: ICT-行业应用 | C82: JTSJCP02209 | D82: 云总机 | E82: 是 | F82: 标品 | I82: 行业应用 | J82: ICT | M82: 1915 | N82: 0.06 | O82: 产业数字化-ICT业务-行业平台及应用-通用信息化标品-智能语音云-云总机 | P82: 1915 | Q82: 产业数字化-ICT业务-行业平台及应用-通用信息化标品-智能语音云-云总机 | R82: 是 | S82: 是 | T82: 无需填写速率/带宽 | U82: 无需填写折扣率
A83: JTSJCPDL201905 | B83: ICT-行业应用 | C83: JTSJCP02118 | D83: 精品专线（国际版） | E83: 是 | F83: 标品 | I83: 行业应用 | J83: ICT | M83: 3032(标）、3087(项) | N83: 0.09 | O83: 产业数字化-资源型服务-组网专线-标品型-普通组网专线-普通组网专线-OTN精品专线-国际及港澳台-境内客户 | P83: 3032;3033;3068;3069;3075;3076 | Q83: 产业数字化-资源型服务-组网专线-标品型-普通组网专线-OTN精品专线-国际及港澳台-境内客户;产业数字化-资源型服务-组网专线-标品型-普通组网专线-OTN精品专线-国际及港澳台-境外客户;产业数字化-资源型服务-组网专线-标品型-普通组网专线-以太专线-国际及港澳台-境内客户;产业数字化-资源型服务-组网专线-标品型-普通组网专线-以太专线-国际及港澳台-境外客户;产业数字化-资源型服务-组网专线-标品型-普通组网专线-IP-VPDN;产业数字化-资源型服务-组网专线-标品型-普通组网专线-国际及港澳台网元业务 | R83: 是 | S83: 是 | T83: 需填写速率/带宽 | U83: 无需填写折扣率
A84: JTSJCPDL201905 | B84: ICT-行业应用 | C84: JTSJCP02099 | D84: 移动护士站 | E84: 是 | F84: 能力 | I84: 行业应用 | J84: ICT | R84: 否 | S84: 是 | T84: 无需填写速率/带宽 | U84: 无需填写折扣率
A85: JTSJCPDL201905 | B85: ICT-行业应用 | C85: JTSJCP04013 | D85: 智慧社区平台 | E85: 是 | F85: 能力 | I85: 行业应用 | J85: ICT | M85: 1986 | N85: 0.06 | O85: 产业数字化-ICT业务-行业平台及应用-行业信息化标品-智慧社区 | P85: 1986 | Q85: 产业数字化-ICT业务-行业平台及应用-行业信息化标品-智慧社区 | R85: 否 | S85: 是 | T85: 无需填写速率/带宽 | U85: 无需填写折扣率
A86: JTSJCPDL201905 | B86: 5G业务 | C86: JTSJCP04031 | D86: 5G定制网网元定制 | E86: 是 | F86: 标品 | I86: 5G业务 | J86: ICT | M86: 1966 | N86: 0.06 | O86: 产业数字化-资源型服务-5G定制网-项目型5G定制网-网元定制 | P86: 1966 | Q86: 产业数字化-资源型服务-5G定制网-项目型5G定制网-网元定制 | R86: 是 | S86: 否 | T86: 无需填写速率/带宽 | U86: 无需填写折扣率
A87: JTSJCPDL201905 | B87: ICT-行业应用 | C87: JTSJCP04060 | D87: 网站安全专家 | E87: 是 | F87: 标品 | I87: 行业应用 | J87: ICT | M87: 1946 | N87: 0.06 | O87: 产业数字化-ICT业务-行业安全产品-云堤服务-网站安全 | P87: 1946 | Q87: 产业数字化-ICT业务-行业安全产品-云堤服务-网站安全 | R87: 是 | S87: 是 | T87: 无需填写速率/带宽 | U87: 无需填写折扣率
A88: JTSJCPDL201905 | B88: ICT-行业应用 | C88: JTSJCP04061 | D88: 域名无忧 | E88: 是 | F88: 标品 | I88: 行业应用 | J88: ICT | M88: 1949 | N88: 0.06 | O88: 产业数字化-ICT业务-行业安全产品-云堤服务-其他 | P88: 1949 | Q88: 产业数字化-ICT业务-行业安全产品-云堤服务-其他 | R88: 是 | S88: 是 | T88: 无需填写速率/带宽 | U88: 无需填写折扣率
A89: JTSJCPDL201905 | B89: ICT-行业应用 | C89: JTSJCP04063 | D89: 隐私哨兵企业版 | E89: 是 | F89: 标品 | I89: 行业应用 | J89: ICT | M89: 1949 | N89: 0.06 | O89: 产业数字化-ICT业务-行业安全产品-云堤服务-其他 | P89: 1949 | Q89: 产业数字化-ICT业务-行业安全产品-云堤服务-其他 | R89: 是 | S89: 是 | T89: 无需填写速率/带宽 | U89: 无需填写折扣率
A90: JTSJCPDL201905 | B90: ICT-行业应用 | C90: JTSJCP04066 | D90: 反诈雷达 | E90: 是 | F90: 能力 | I90: 行业应用 | J90: ICT | M90: 1949 | N90: 0.06 | O90: 产业数字化-ICT业务-行业安全产品-云堤服务-其他 | P90: 1949 | Q90: 产业数字化-ICT业务-行业安全产品-云堤服务-其他 | R90: 否 | S90: 是 | T90: 无需填写速率/带宽 | U90: 无需填写折扣率
A91: JTSJCPDL201905 | B91: ICT-行业应用 | C91: JTSJCP04067 | D91: 广目 | E91: 是 | F91: 能力 | I91: 行业应用 | J91: ICT | M91: 1949 | N91: 0.06 | O91: 产业数字化-ICT业务-行业安全产品-云堤服务-其他 | P91: 1949 | Q91: 产业数字化-ICT业务-行业安全产品-云堤服务-其他 | R91: 否 | S91: 是 | T91: 无需填写速率/带宽 | U91: 无需填写折扣率
A92: JTSJCPDL201905 | B92: 5G业务 | C92: JTSJCP04030 | D92: 5G工作手机 | E92: 是 | F92: 标品 | I92: 5G业务 | R92: 是 | S92: 是 | T92: 无需填写速率/带宽 | U92: 无需填写折扣率
A93: JTSJCPDL201905 | B93: 5G业务 | C93: JTSJCP04006 | D93: 5G定制网超级号卡 | E93: 是 | F93: 标品 | I93: 5G业务 | M93: 1726 | N93: 0.06 | O93: 产业数字化-资源型服务-5G定制网-标品型5G定制网-超级号卡 | P93: 1726 | Q93: 产业数字化-资源型服务-5G定制网-标品型5G定制网-超级号卡 | R93: 是 | S93: 是 | T93: 无需填写速率/带宽 | U93: 无需填写折扣率
A94: JTSJCPDL201905 | B94: 5G业务 | C94: JTSJCP01130 | D94: 5G双域快网 | E94: 否 | F94: 标品 | M94: 1966 | N94: 0.06 | O94: 产业数字化-资源型服务-5G定制网-项目型5G定制网-网元定制 | P94: 1726;1966 | Q94: 产业数字化-资源型服务-5G定制网-标品型5G定制网-超级号卡;产业数字化-资源型服务-5G定制网-项目型5G定制网-网元定制 | R94: 是 | S94: 是 | T94: 无需填写速率/带宽 | U94: 无需填写折扣率
A95: JTSJCPDL201905 | B95: 5G业务 | C95: JTSJCP03011 | D95: 5G商企专网 | E95: 是 | F95: 标品 | I95: 5G | M95: 1966 | N95: 0.06 | O95: 产业数字化-资源型服务-5G定制网-项目型5G定制网-网元定制 | P95: 1966 | Q95: 产业数字化-资源型服务-5G定制网-项目型5G定制网-网元定制 | R95: 是 | S95: 是 | T95: 无需填写速率/带宽 | U95: 无需填写折扣率
A96: JTSJCPDL201905 | B96: ICT-行业应用 | C96: JTSJCP01144 | D96: 社会治理大数据中脑 | E96: 是 | F96: 标品 | I96: 行业数字平台和应用 | M96: 2408 | N96: 0.06 | O96: 产业数字化-ICT业务-行业平台及应用-行业数字平台 | P96: 2408 | Q96: 产业数字化-ICT业务-行业平台及应用-行业数字平台 | R96: 是 | S96: 是 | T96: 无需填写速率/带宽 | U96: 无需填写折扣率
A97: JTSJCPDL201905 | B97: ICT-行业应用 | C97: JTSJCP01145 | D97: 翼平台框架产品 | E97: 是 | F97: 标品 | I97: 行业数字平台和应用 | M97: 2408 | N97: 0.06 | O97: 产业数字化-ICT业务-行业平台及应用-行业数字平台 | P97: 2408 | Q97: 产业数字化-ICT业务-行业平台及应用-行业数字平台 | R97: 是 | S97: 是 | T97: 无需填写速率/带宽 | U97: 无需填写折扣率
A98: JTSJCPDL201905 | B98: ICT-行业应用 | C98: JTSJCP01146 | D98: 翼安巡防 | E98: 是 | F98: 标品 | I98: 行业数字平台和应用 | M98: 2408 | N98: 0.06 | O98: 产业数字化-ICT业务-行业平台及应用-行业数字平台 | P98: 2408 | Q98: 产业数字化-ICT业务-行业平台及应用-行业数字平台 | R98: 是 | S98: 是 | T98: 无需填写速率/带宽 | U98: 无需填写折扣率
A99: JTSJCPDL201905 | B99: ICT-行业应用 | C99: JTSJCP01147 | D99: 翼云店 | E99: 是 | F99: 标品 | I99: 行业数字平台和应用 | M99: 2408 | N99: 0.06 | O99: 产业数字化-ICT业务-行业平台及应用-行业数字平台 | P99: 2408 | Q99: 产业数字化-ICT业务-行业平台及应用-行业数字平台 | R99: 是 | S99: 是 | T99: 无需填写速率/带宽 | U99: 无需填写折扣率
A100: JTSJCPDL201905 | B100: ICT-行业应用 | C100: JTSJCP01008 | D100: 智慧养老 | E100: 是 | F100: 标品 | G100: 户 | H100: 开通功能的用户数 | I100: 行业应用 | J100: ICT | M100: 2408 | N100: 0.06 | O100: 产业数字化-ICT业务-行业平台及应用-行业数字平台 | P100: 2408 | Q100: 产业数字化-ICT业务-行业平台及应用-行业数字平台 | R100: 是 | S100: 是 | T100: 无需填写速率/带宽 | U100: 无需填写折扣率
...

Sheet 税率配置表&利润中心
A1: 指标编码 | B1: 指标名称 | C1: 税率 | D1: 税目（默认带出） | F1: 备注 | G1: 利润中心
A2: 1006 | B2: 移动通信服务-移动语音-语音收入-国内通话费 | C2: 0.09 | D2: 电信业——基础电信服务——语音服务 | G2: 总部部门
A3: 3155 | B3: 移动通信服务-移动语音-语音收入-国际、港澳台通话费 | C3: 0.09 | D3: 电信业——基础电信服务——语音服务 | G3: 工程建设中心
A4: 3156 | B4: 移动通信服务-移动语音-语音收入-国际、港澳台漫游费通话费-漫游语音包通话费 | C4: 0.09 | D4: 电信业——基础电信服务——语音服务 | G4: 市场部
A5: 3157 | B5: 移动通信服务-移动语音-语音收入-国际、港澳台漫游费通话费-漫游非语音包通话费 | C5: 0.09 | D5: 电信业——基础电信服务——语音服务 | G5: 渠道运营支撑中心（待迁移）
A6: 1024 | B6: 移动通信服务-移动语音-语音收入-移动语音结算-移动语音上市非上市结算 | C6: 0.09 | D6: 电信业——基础电信服务——语音服务 | G6: 云网运营部
A7: 1027 | B7: 移动通信服务-移动语音-语音收入-移动语音结算-移动语音漫游结算 | C7: 0.09 | D7: 电信业——基础电信服务——语音服务 | G7: 上海电信信息世界
A8: 1031 | B8: 移动通信服务-移动语音-语音收入-移动语音结算-移动语音网间结算-国内运营商网间结算-本地网网间结算-中国移动 | C8: 0.09 | D8: 电信业——基础电信服务——语音服务 | G8: 政企事业群
A9: 1032 | B9: 移动通信服务-移动语音-语音收入-移动语音结算-移动语音网间结算-国内运营商网间结算-本地网网间结算-中国联通 | C9: 0.09 | D9: 电信业——基础电信服务——语音服务 | G9: 上海电信EDI分公司
A10: 1967 | B10: 移动通信服务-移动语音-语音收入-移动语音结算-移动语音网间结算-国内运营商网间结算-本地网网间结算-中国广电 | C10: 0.09 | D10: 电信业——基础电信服务——语音服务 | G10: 业创中心
A11: 1034 | B11: 移动通信服务-移动语音-语音收入-移动语音结算-移动语音网间结算-国内运营商网间结算-国内长途网间结算-中国移动 | C11: 0.09 | D11: 电信业——基础电信服务——语音服务 | G11: 上海公司融合创新研发基地
A12: 1035 | B12: 移动通信服务-移动语音-语音收入-移动语音结算-移动语音网间结算-国内运营商网间结算-国内长途网间结算-中国联通 | C12: 0.09 | D12: 电信业——基础电信服务——语音服务 | G12: 总部集中控制
A13: 2037 | B13: 移动通信服务-移动语音-语音收入-移动语音结算-移动语音网间结算-国内运营商网间结算-国内长途网间结算-中国广电 | C13: 0.09 | D13: 电信业——基础电信服务——语音服务 | G13: 东区局分公司
A14: 1036 | B14: 移动通信服务-移动语音-语音收入-移动语音结算-移动语音网间结算-国际、港澳台运营商网间结算 | C14: 0 | D14: 免税收入 | E14: 免税收入 | F14: 关注 | G14: 南区局分公司
A15: 1037 | B15: 移动通信服务-移动语音-语音收入-移动语音结算-国际及港澳台运营商漫游结算 | C15: 0 | D15: 免税收入 | E15: 免税收入 | F15: 关注 | G15: 西区局分公司
A16: 2961 | B16: 移动通信服务-移动语音-其他 | C16: 0.09 | D16: 电信业——基础电信服务——语音服务 | G16: 北区局分公司
A17: 1042 | B17: 移动通信服务-手机上网-套内流量 | C17: 0.06 | D17: 电信业——增值电信服务——互联网接入服务 | G17: 中区局分公司
A18: 1043 | B18: 移动通信服务-手机上网-套外标准资费 | C18: 0.06 | D18: 电信业——增值电信服务——互联网接入服务 | G18: 浦东局分公司
A19: 2702 | B19: 移动通信服务-手机上网-流量包-权益包模式流量包 | C19: 0.06 | D19: 电信业——增值电信服务——互联网接入服务 | G19: 宝山局分公司
A20: 2703 | B20: 移动通信服务-手机上网-流量包-非权益包模式流量包 | C20: 0.06 | D20: 电信业——增值电信服务——互联网接入服务 | G20: 莘闵局分公司
A21: 1046 | B21: 移动通信服务-手机上网-定向流量-权益包模式定向流量 | C21: 0.06 | D21: 电信业——增值电信服务——互联网接入服务 | G21: 嘉定局分公司
A22: 1047 | B22: 移动通信服务-手机上网-定向流量-非权益包模式定向流量 | C22: 0.06 | D22: 电信业——增值电信服务——互联网接入服务 | G22: 奉贤局分公司
A23: 1049 | B23: 移动通信服务-手机上网-后向流量-后向定向流量 | C23: 0.06 | D23: 电信业——增值电信服务——互联网接入服务 | G23: 金山局分公司
A24: 1052 | B24: 移动通信服务-手机上网-后向流量-后向非定向流量 | C24: 0.06 | D24: 电信业——增值电信服务——互联网接入服务 | G24: 青浦局分公司
A25: 2962 | B25: 移动通信服务-手机上网-移动数据漫游-国际及港澳台漫游流量包 | C25: 0.06 | D25: 电信业——增值电信服务——互联网接入服务 | G25: 松江局分公司
A26: 3158 | B26: 移动通信服务-手机上网-移动数据漫游-国际及港澳台漫游非流量包 | C26: 0.06 | D26: 电信业——增值电信服务——互联网接入服务 | G26: 崇明局分公司
A27: 1085 | B27: 移动通信服务-手机上网-移动数据结算-网内结算-移动流量漫游结算 | C27: 0.06 | D27: 电信业——增值电信服务——互联网接入服务 | G27: 移互部/移动网优中心/上海5G共建共享工
A28: 1086 | B28: 移动通信服务-手机上网-移动数据结算-网内结算-天翼宽带漫游结算 | C28: 0.06 | D28: 电信业——增值电信服务——互联网接入服务 | G28: 信网部/互联网大客户部
A29: 2673 | B29: 移动通信服务-手机上网-移动数据结算-国际、港澳台漫游结算 | C29: 0 | D29: 免税收入 | E29: 免税收入 | F29: 关注 | G29: 数字生活部/互联网部
A30: 1060 | B30: 移动通信服务-手机上网-其他 | C30: 0.06 | D30: 电信业——增值电信服务——互联网接入服务 | G30: 智慧商务部/号百公司
A31: 3159 | B31: 移动通信服务-移动消息-短彩信收入-短信-发国内点对点短信收入 | C31: 0.06 | D31: 电信业——增值电信服务——短彩信服务 | G31: 罗泾信息网络中心
A32: 3160 | B32: 移动通信服务-移动消息-短彩信收入-短信-发国际、港澳台点对点短信收入 | C32: 0.06 | D32: 电信业——增值电信服务——短彩信服务 | G32: 桃浦信息网络中心
A33: 3161 | B33: 移动通信服务-移动消息-短彩信收入-短信-国际、港澳台漫游短信收入 | C33: 0.06 | D33: 电信业——增值电信服务——短彩信服务 | G33: 数字政务服务中心
A34: 2705 | B34: 移动通信服务-移动消息-短彩信收入-短信-SP短信信息费收入-收入（大收） | C34: 0.06 | D34: 电信业——增值电信服务——短彩信服务 | G34: 上海公司智慧家庭运营中心
A35: 1074 | B35: 移动通信服务-移动消息-短彩信收入-短信-SP短信信息费收入-CP/SP结算支出 | C35: 0.06 | D35: 电信业——增值电信服务——短彩信服务 | G35: 卓青信息网络中心
A36: 1075 | B36: 移动通信服务-移动消息-短彩信收入-彩信 | C36: 0.06 | D36: 电信业——增值电信服务——短彩信服务 | G36: 泖南数据服务分部
A37: 1968 | B37: 移动通信服务-移动消息-个人5G消息 | C37: 0.06 | D37: 电信业——增值电信服务——短彩信服务 | G37: 金泽数据服务分部
A38: 1165 | B38: 移动通信服务-移动消息-信息订制（净收）-收入（大收） | C38: 0.06 | D38: 电信业——增值电信服务——电子数据和信息的传输及应用服务 | G38: 机动局
A39: 1166 | B39: 移动通信服务-移动消息-信息订制（净收）-CP/SP结算支出 | C39: 0.06 | D39: 电信业——增值电信服务——电子数据和信息的传输及应用服务 | G39: 业务管理支撑中心
A40: 1080 | B40: 移动通信服务-移动消息-行业类消息-行业短彩信-行业短信 | C40: 0.06 | D40: 电信业——增值电信服务——短彩信服务 | G40: 信息园区开发建设部/房屋与土地资产运营中
A41: 1081 | B41: 移动通信服务-移动消息-行业类消息-行业短彩信-行业彩信 | C41: 0.06 | D41: 电信业——增值电信服务——短彩信服务 | G41: 上海ICNOC
... A50: 1098 | B50: 移动通信服务-移动消息-消息结算-国内运营商网间结算-彩信结算-中国联通 | C50: 0.06 | D50: 电信业——增值电信服务——短彩信服务 | G50: 政务大客户部/重大项目管理办公室
A51: 3162 | B51: 移动通信服务-移动消息-消息结算-国际、港澳台运营商网间结算 | C51: 0 | D51: 免税收入 | E51: 免税收入 | F51: 关注 | G51: 公共服务大客户部
A52: 1099 | B52: 移动通信服务-移动消息-消息结算-国际及港澳台运营商短信漫游结算 | C52: 0 | D52: 免税收入 | E52: 免税收入 | F52: 关注 | G52: 金融大客户部
A53: 1088 | B53: 移动通信服务-移动消息-消息结算-行业短彩信结算-行业短信结算 | C53: 0.06 | D53: 电信业——增值电信服务——短彩信服务 | G53: 工业和服务业大客户部
A54: 1089 | B54: 移动通信服务-移动消息-消息结算-行业短彩信结算-行业彩信结算 | C54: 0.06 | D54: 电信业——增值电信服务——短彩信服务 | G54: 战略大客户部
A55: 1065 | B55: 移动通信服务-移动增值业务-副卡功能费 | C55: 0.06 | D55: 电信业——增值电信服务——电子数据和信息的传输及应用服务 | G55: 渠道运营支撑中心
A56: 1063 | B56: 移动通信服务-移动增值业务-来电显示 | C56: 0.06 | D56: 电信业——增值电信服务——电子数据和信息的传输及应用服务 | G56: 公众客户部/天翼终端公司上海分公司
A57: 1064 | B57: 移动通信服务-移动增值业务-停机保号 | C57: 0.06 | D57: 电信业——增值电信服务——电子数据和信息的传输及应用服务 | G57: 网络和信息安全部
A58: 1082 | B58: 移动通信服务-移动增值业务-天翼亲情网 | C58: 0.06 | D58: 电信业——增值电信服务——电子数据和信息的传输及应用服务 | G58: 天翼云能力运营中心/数字政务服务中心
A59: 1192 | B59: 移动通信服务-移动增值业务-统一账号 | C59: 0.06 | D59: 电信业——增值电信服务——电子数据和信息的传输及应用服务 | G59: 公共服务中心
A60: 1108 | B60: 移动通信服务-移动增值业务-其他 | C60: 0.06 | D60: 电信业——增值电信服务——电子数据和信息的传输及应用服务 | G60: 科创大客户部
A61: 2943 | B61: 移动通信服务-移动信息化应用-个人云产品-天翼云盘-基础功能费 | C61: 0.06 | D61: 电信业——增值电信服务——电子数据和信息的传输及应用服务 | G61: 中网院电信运营中心
A62: 2944 | B62: 移动通信服务-移动信息化应用-个人云产品-天翼云盘-会员服务费 | C62: 0.06 | D62: 电信业——增值电信服务——电子数据和信息的传输及应用服务 | G62: 海卓项目组
A63: 1119 | B63: 移动通信服务-移动信息化应用-个人云产品-天翼云手机 | C63: 0.06 | D63: 电信业——增值电信服务——电子数据和信息的传输及应用服务 | G63: 智能云网业务运营中心
A64: 1159 | B64: 移动通信服务-移动信息化应用-个人AI产品-AI通信助理（净收）-收入（大收） | C64: 0.06 | D64: 电信业——增值电信服务——电子数据和信息的传输及应用服务 | G64: 上海研究院
... A69: 1125 | B69: 移动通信服务-移动信息化应用-个人安全产品-天翼防骚扰 | C69: 0.06 | D69: 电信业——增值电信服务——电子数据和信息的传输及应用服务 | G69: 天翼云科技有限公司上海分公司
A70: 1126 | B70: 移动通信服务-移动信息化应用-个人安全产品-其他 | C70: 0.06 | D70: 电信业——增值电信服务——电子数据和信息的传输及应用服务
A71: 3047 | B71: 移动通信服务-移动信息化应用-卫星移动业务-合作星 | C71: 9.0%/6.0% | D71: 电信业——基础电信服务——语音服务 电信业——增值电信服务——电子数据和信息的传输及应用服务 电信业——增值电信服务——短彩信服务 | E71: 结合业务实质判断并准确选择适用税率 | F71: 关注
A72: 3048 | B72: 移动通信服务-移动信息化应用-卫星移动业务-天通卫星 | C72: 9.0%/6.0% | D72: 电信业——基础电信服务——语音服务 电信业——增值电信服务——电子数据和信息的传输及应用服务 电信业——增值电信服务——短彩信服务 | E72: 结合业务实质判断并准确选择适用税率 | F72: 关注
A73: 3049 | B73: 移动通信服务-移动信息化应用-卫星移动业务-手机直连卫星 | C73: 9.0%/6.0% | D73: 电信业——基础电信服务——语音服务 电信业——增值电信服务——电子数据和信息的传输及应用服务 电信业——增值电信服务——短彩信服务 | E73: 结合业务实质判断并准确选择适用税率 | F73: 关注
A74: 3050 | B74: 移动通信服务-移动信息化应用-卫星移动业务-汽车直连卫星 | C74: 9.0%/6.0% | D74: 电信业——基础电信服务——语音服务 电信业——增值电信服务——电子数据和信息的传输及应用服务 电信业——增值电信服务——短彩信服务 | E74: 结合业务实质判断并准确选择适用税率 | F74: 关注
A75: 3051 | B75: 移动通信服务-移动信息化应用-卫星移动业务-其他 | C75: 9.0%/6.0% | D75: 电信业——基础电信服务——语音服务 电信业——增值电信服务——电子数据和信息的传输及应用服务 电信业——增值电信服务——短彩信服务 | E75: 结合业务实质判断并准确选择适用税率 | F75: 关注
A76: 1123 | B76: 移动通信服务-移动信息化应用-量子密话-收入（大收） | C76: 0.06 | D76: 电信业——增值电信服务——电子数据和信息的传输及应用服务
A77: 1124 | B77: 移动通信服务-移动信息化应用-量子密话-CP/SP结算支出 | C77: 0.06 | D77: 电信业——增值电信服务——电子数据和信息的传输及应用服务
A78: 2726 | B78: 移动通信服务-移动信息化应用-移动内容服务-移动用户音乐内容服务-公众用户视频彩铃-AI视频彩铃-功能费 | C78: 0.06 | D78: 电信业——增值电信服务——电子数据和信息的传输及应用服务
A79: 2728 | B79: 移动通信服务-移动信息化应用-移动内容服务-移动用户音乐内容服务-公众用户视频彩铃-AI视频彩铃-信息费-收入（大收） | C79: 0.06 | D79: 电信业——增值电信服务——电子数据和信息的传输及应用服务
A80: 2729 | B80: 移动通信服务-移动信息化应用-移动内容服务-移动用户音乐内容服务-公众用户视频彩铃-AI视频彩铃-信息费-CP/SP结算支出 | C80: 0.06 | D80: 电信业——增值电信服务——电子数据和信息的传输及应用服务
A81: 3228 | B81: 移动通信服务-移动信息化应用-移动内容服务-移动用户音乐内容服务-公众用户视频彩铃-AI视频彩铃-天翼智铃 | C81: 0.06 | D81: 电信业——增值电信服务——电子数据和信息的传输及应用服务
A82: 1134 | B82: 移动通信服务-移动信息化应用-移动内容服务-移动用户音乐内容服务-公众用户视频彩铃-普通视频彩铃-功能费 | C82: 0.06 | D82: 电信业——增值电信服务——电子数据和信息的传输及应用服务
A83: 1136 | B83: 移动通信服务-移动信息化应用-移动内容服务-移动用户音乐内容服务-公众用户视频彩铃-普通视频彩铃-信息费-收入（大收） | C83: 0.06 | D83: 电信业——增值电信服务——电子数据和信息的传输及应用服务
A84: 1137 | B84: 移动通信服务-移动信息化应用-移动内容服务-移动用户音乐内容服务-公众用户视频彩铃-普通视频彩铃-信息费-CP/SP结算支出 | C84: 0.06 | D84: 电信业——增值电信服务——电子数据和信息的传输及应用服务
A85: 1139 | B85: 移动通信服务-移动信息化应用-移动内容服务-移动用户音乐内容服务-政企用户视频彩铃-功能费 | C85: 0.06 | D85: 电信业——增值电信服务——电子数据和信息的传输及应用服务
A86: 1141 | B86: 移动通信服务-移动信息化应用-移动内容服务-移动用户音乐内容服务-政企用户视频彩铃-信息费-收入（大收） | C86: 0.06 | D86: 电信业——增值电信服务——电子数据和信息的传输及应用服务
A87: 1142 | B87: 移动通信服务-移动信息化应用-移动内容服务-移动用户音乐内容服务-政企用户视频彩铃-信息费-CP/SP结算支出 | C87: 0.06 | D87: 电信业——增值电信服务——电子数据和信息的传输及应用服务
... A110: 2890 | B110: 移动通信服务-移动信息化应用-移动内容服务-其他-CP/SP结算支出 | C110: 0.06 | D110: 电信业——增值电信服务——电子数据和信息的传输及应用服务
A111: 1204 | B111: 移动通信服务-其他移动通信服务-移动通信网络资源服务收入-移动通信设备共享服务收入-机房及配套资源合作收入 | C111: 9%、3% | D111: 经营租赁——不动产租赁 | E111: 各省按实际确定是否简易征收 | F111: 关注
A112: 1205 | B112: 移动通信服务-其他移动通信服务-移动通信网络资源服务收入-移动通信设备共享服务收入-传输线路资源合作收入 | C112: 0.09 | D112: 电信业——基础电信服务——网络元素使用服务
A113: 1206 | B113: 移动通信服务-其他移动通信服务-移动通信网络资源服务收入-移动通信设备共享服务收入-其他共享合作收入 | C113: 9%/6% | D113: 电信业——基础电信服务——网络元素使用服务 电信业——增值电信服务——互联网接入服务 | E113: 结合业务实质判断并准确选择适用税率 | F113: 关注
A114: 2700 | B114: 移动通信服务-其他移动通信服务-移动通信网络资源服务收入-移动网络能力共享服务收入-4G移动网络能力共享服务收入 | C114: 0.06 | D114: 电信业——增值电信服务——互联网接入服务
A115: 2701 | B115: 移动通信服务-其他移动通信服务-移动通信网络资源服务收入-移动网络能力共享服务收入-其他 | C115: 9%/6% | D115: 电信业——基础电信服务——网络元素使用服务 电信业——增值电信服务——互联网接入服务 | E115: 结合业务实质判断并准确选择适用税率 | F115: 关注
A116: 1208 | B116: 移动通信服务-其他移动通信服务-移动通信网络资源服务收入-移动其他网络资源服务收入 | C116: 9%/6% | D116: 电信业——基础电信服务——网络元素使用服务 电信业——增值电信服务——互联网接入服务 | E116: 结合业务实质判断并准确选择适用税率 | F116: 关注
A117: 1210 | B117: 移动通信服务-其他移动通信服务-移动转售收入-语音收入 | C117: 0.09 | D117: 电信业——基础电信服务——语音服务
A118: 1211 | B118: 移动通信服务-其他移动通信服务-移动转售收入-短信收入 | C118: 0.06 | D118: 电信业——增值电信服务——短彩信服务
A119: 1212 | B119: 移动通信服务-其他移动通信服务-移动转售收入-流量收入 | C119: 0.06 | D119: 电信业——增值电信服务——互联网接入服务
A120: 1213 | B120: 移动通信服务-其他移动通信服务-移动转售收入-其他增值收入 | C120: 0.06 | D120: 电信业——增值电信服务——电子数据和信息的传输及应用服务
A121: 1183 | B121: 移动通信服务-其他移动通信服务-移动相关品牌及广告-百事通加盟收入（净收）-收入（大收） | C121: 0.06 | D121: 电信业——增值电信服务——电子数据和信息的传输及应用服务
A122: 1184 | B122: 移动通信服务-其他移动通信服务-移动相关品牌及广告-百事通加盟收入（净收）-CP/SP结算支出 | C122: 0.06 | D122: 电信业——增值电信服务——电子数据和信息的传输及应用服务
A123: 1188 | B123: 移动通信服务-其他移动通信服务-移动相关品牌及广告-移动广告 | C123: 0.06 | D123: 现代服务业——文化创意服务——广告业务
A124: 1195 | B124: 移动通信服务-其他移动通信服务-移动相关品牌及广告-其他 | C124: 0.06 | D124: 电信业——增值电信服务——电子数据和信息的传输及应用服务
A125: 1197 | B125: 移动通信服务-其他移动通信服务-无线宽带收入 | C125: 0.06 | D125: 电信业——增值电信服务——互联网接入服务
A126: 1420 | B126: 移动通信服务-其他移动通信服务-数字集群收入 | C126: 0.06 | D126: 电信业——增值电信服务——电子数据和信息的传输及应用服务
A127: 1214 | B127: 移动通信服务-其他移动通信服务-其他 | E127: 结合业务实质判断并准确选择适用税率 | F127: 关注
A128: 1222 | B128: 固网及智慧家庭服务-固定电话-固网语音-装移机收入 | C128: 0.09 | D128: 建筑服务-安装服务
A129: 1227 | B129: 固网及智慧家庭服务-固定电话-固网语音-语音收入-本地通话费 | C129: 0.09 | D129: 电信业——基础电信服务——语音服务
A130: 1228 | B130: 固网及智慧家庭服务-固定电话-固网语音-语音收入-国内长途通话费 | C130: 0.09 | D130: 电信业——基础电信服务——语音服务
A131: 1229 | B131: 固网及智慧家庭服务-固定电话-固网语音-语音收入-国内通话费 | C131: 0.09 | D131: 电信业——基础电信服务——语音服务
A132: 3165 | B132: 固网及智慧家庭服务-固定电话-固网语音-语音收入-国际、港澳台长途通话费 | C132: 0.09 | D132: 电信业——基础电信服务——语音服务
A133: 1234 | B133: 固网及智慧家庭服务-固定电话-固网语音-后向收入（400/800） | C133: 0.09 | D133: 电信业——基础电信服务——语音服务
A134: 1237 | B134: 固网及智慧家庭服务-固定电话-固网语音-固网语音结算-固网语音上市非上市结算-固网本地结算 | C134: 0.09 | D134: 电信业——基础电信服务——语音服务
...

Sheet 业务模式和列收方式判断规则
A1: 业务模式 | B1: 列收方式（总额/净额） | C1: 列收方式（非周期型） | D1: 列收方式（投入/产出） | F1: 业务模式 | G1: 列收方式（总额/净额） | H1: 列收方式（周期型）
A2: 设备经销商租赁 | B2: 总额法、时点法 | C2: 非周期型 | F2: 投资-经营租赁 | G2: 总额法、时段法 | H2: 周期型
A3: 设备买卖 | B3: 总额法、时点法 | C3: 非周期型 | F3: 投资-集成服务 | G3: 总额法、时段法 | H3: 周期型
A4: 设备受托代购 | B4: 净额法、时点法 | C4: 非周期型 | F4: 服务整合 | G4: 总额法、时段法 | H4: 周期型
A5: 设备转租赁 | B5: 净额法、时点法 | C5: 非周期型 | F5: 服务代理 | G5: 净额法、时段法 | H5: 周期型
A6: 服务整合 | B6: 总额法、时段法 | C6: 非周期型 | D6: 投入法/产出法 | F6: 设备与第三方合作 | G6: 净额法、时段法 | H6: 周期型
A7: 服务整合 | B7: 总额法、时点法 | C7: 非周期型
A8: 服务代理 | B8: 净额法、时段法 | C8: 非周期型 | D8: 产出法
A9: 服务代理 | B9: 净额法、时点法 | C9: 非周期型
A10: 设备与第三方合作 | B10: 净额法、时段法 | C10: 非周期型 | D10: 产出法
A11: 设备与第三方合作 | B11: 净额法、时点法 | C11: 非周期型
A14: 业务模式与列收方式-非周期 | C14: 业务模式与列收方式-周期
A15: 服务整合、总额法、时段法、投入法 | C15: 投资-经营租赁、总额法、时段法
A16: 服务整合、总额法、时段法、产出法 | C16: 投资-集成服务、总额法、时段法
A17: 服务整合、总额法、时点法 | C17: 服务整合、总额法、时段法
A18: 服务代理、净额法、时段法、产出法 | C18: 服务代理、净额法、时段法
A19: 服务代理、净额法、时点法 | C19: 设备与第三方合作、净额法、时段法
A20: 设备买卖、总额法、时点法
A21: 设备受托代购、净额法、时点法
A22: 设备经销商租赁、总额法、时点法
A23: 设备转租赁、净额法、时点法
A24: 设备与第三方合作、净额法、时段法、产出法
A25: 设备与第三方合作、净额法、时点法
